<?xml version="1.0" encoding="UTF-8"?>
<!DOCTYPE chunkList SYSTEM "ccl.dtd">
<chunkList>
 <chunk id="ch1">
  <sentence id="sent1">
   <tok>
    <orth>Bitwa</orth>
    <lex disamb="1"><base>bitwa</base><ctag>subst:sg:nom:f</ctag></lex>
    <ann chan="nam">1</ann>
   </tok>
   <tok>
    <orth>pod</orth>
    <lex><base>POD</base><ctag>subst:pl:nom:n</ctag></lex>
    <lex><base>POD</base><ctag>subst:pl:gen:n</ctag></lex>
    <lex><base>POD</base><ctag>subst:pl:dat:n</ctag></lex>
    <lex><base>POD</base><ctag>subst:pl:acc:n</ctag></lex>
    <lex><base>POD</base><ctag>subst:pl:inst:n</ctag></lex>
    <lex><base>POD</base><ctag>subst:pl:loc:n</ctag></lex>
    <lex><base>POD</base><ctag>subst:pl:voc:n</ctag></lex>
    <lex><base>pod</base><ctag>prep:acc:nwok</ctag></lex>
    <lex disamb="1"><base>pod</base><ctag>prep:inst:nwok</ctag></lex>
    <ann chan="nam">1</ann>
   </tok>
   <tok>
    <orth>Lublinem</orth>
    <lex disamb="1"><base>Lublin</base><ctag>subst:sg:inst:m3</ctag></lex>
    <lex disamb="1"><base>lublin</base><ctag>subst:sg:inst:m3</ctag></lex>
    <ann chan="nam">1</ann>
   </tok>
  </sentence>
 </chunk>
 <chunk id="ch2">
  <sentence id="sent2">
   <tok>
    <orth>Bitwa</orth>
    <lex disamb="1"><base>bitwa</base><ctag>subst:sg:nom:f</ctag></lex>
    <ann chan="nam">1</ann>
   </tok>
   <tok>
    <orth>pod</orth>
    <lex><base>POD</base><ctag>subst:pl:nom:n</ctag></lex>
    <lex><base>POD</base><ctag>subst:pl:gen:n</ctag></lex>
    <lex><base>POD</base><ctag>subst:pl:dat:n</ctag></lex>
    <lex><base>POD</base><ctag>subst:pl:acc:n</ctag></lex>
    <lex><base>POD</base><ctag>subst:pl:inst:n</ctag></lex>
    <lex><base>POD</base><ctag>subst:pl:loc:n</ctag></lex>
    <lex><base>POD</base><ctag>subst:pl:voc:n</ctag></lex>
    <lex><base>pod</base><ctag>prep:acc:nwok</ctag></lex>
    <lex disamb="1"><base>pod</base><ctag>prep:inst:nwok</ctag></lex>
    <ann chan="nam">1</ann>
   </tok>
   <tok>
    <orth>Lublinem</orth>
    <lex disamb="1"><base>Lublin</base><ctag>subst:sg:inst:m3</ctag></lex>
    <lex disamb="1"><base>lublin</base><ctag>subst:sg:inst:m3</ctag></lex>
    <ann chan="nam">1</ann>
   </tok>
   <tok>
    <orth>–</orth>
    <lex disamb="1"><base>–</base><ctag>interp</ctag></lex>
    <ann chan="nam">0</ann>
   </tok>
   <tok>
    <orth>bitwa</orth>
    <lex disamb="1"><base>bitwa</base><ctag>subst:sg:nom:f</ctag></lex>
    <ann chan="nam">0</ann>
   </tok>
   <tok>
    <orth>pomiędzy</orth>
    <lex><base>pomiędzy</base><ctag>prep:acc</ctag></lex>
    <lex disamb="1"><base>pomiędzy</base><ctag>prep:inst</ctag></lex>
    <ann chan="nam">0</ann>
   </tok>
   <tok>
    <orth>Polakami</orth>
    <lex disamb="1"><base>Polak</base><ctag>subst:pl:inst:m1</ctag></lex>
    <lex><base>polak</base><ctag>subst:pl:inst:m2</ctag></lex>
    <ann chan="nam">2</ann>
   </tok>
   <tok>
    <orth>a</orth>
    <lex disamb="1"><base>a</base><ctag>conj</ctag></lex>
    <lex><base>a</base><ctag>interj</ctag></lex>
    <lex><base>a</base><ctag>prep:nom</ctag></lex>
    <lex><base>a</base><ctag>qub</ctag></lex>
    <lex><base>albo</base><ctag>brev:pun</ctag></lex>
    <ann chan="nam">0</ann>
   </tok>
   <tok>
    <orth>Tatarami</orth>
    <lex disamb="1"><base>Tatar</base><ctag>subst:pl:inst:m1</ctag></lex>
    <lex><base>tatar</base><ctag>subst:pl:inst:m2</ctag></lex>
    <lex><base>tatar</base><ctag>subst:pl:inst:m3</ctag></lex>
    <ann chan="nam">3</ann>
   </tok>
   <tok>
    <orth>stoczona</orth>
    <lex disamb="1"><base>stoczyć</base><ctag>ppas:sg:nom:f:perf:aff</ctag></lex>
    <ann chan="nam">0</ann>
   </tok>
   <tok>
    <orth>w</orth>
    <lex><base>w</base><ctag>prep:acc:nwok</ctag></lex>
    <lex disamb="1"><base>w</base><ctag>prep:loc:nwok</ctag></lex>
    <lex><base>wiek</base><ctag>brev:pun</ctag></lex>
    <lex><base>wielki</base><ctag>brev:pun</ctag></lex>
    <lex><base>wiersz</base><ctag>brev:pun</ctag></lex>
    <lex><base>wieś</base><ctag>brev:pun</ctag></lex>
    <lex><base>wyspa</base><ctag>brev:pun</ctag></lex>
    <ann chan="nam">0</ann>
   </tok>
   <tok>
    <orth>lutym</orth>
    <lex><base>luty</base><ctag>adj:sg:inst:m1:pos</ctag></lex>
    <lex><base>luty</base><ctag>adj:sg:loc:m1:pos</ctag></lex>
    <lex><base>luty</base><ctag>adj:sg:inst:m2:pos</ctag></lex>
    <lex><base>luty</base><ctag>adj:sg:loc:m2:pos</ctag></lex>
    <lex><base>luty</base><ctag>adj:sg:inst:m3:pos</ctag></lex>
    <lex><base>luty</base><ctag>adj:sg:loc:m3:pos</ctag></lex>
    <lex><base>luty</base><ctag>adj:sg:inst:n:pos</ctag></lex>
    <lex><base>luty</base><ctag>adj:sg:loc:n:pos</ctag></lex>
    <lex><base>luty</base><ctag>adj:pl:dat:m1:pos</ctag></lex>
    <lex><base>luty</base><ctag>adj:pl:dat:m2:pos</ctag></lex>
    <lex><base>luty</base><ctag>adj:pl:dat:m3:pos</ctag></lex>
    <lex><base>luty</base><ctag>adj:pl:dat:f:pos</ctag></lex>
    <lex><base>luty</base><ctag>adj:pl:dat:n:pos</ctag></lex>
    <lex><base>luty</base><ctag>subst:sg:inst:m3</ctag></lex>
    <lex disamb="1"><base>luty</base><ctag>subst:sg:loc:m3</ctag></lex>
    <lex><base>luty</base><ctag>subst:pl:dat:m3</ctag></lex>
    <ann chan="nam">0</ann>
   </tok>
   <tok>
    <orth>1341</orth>
    <lex><base>1341</base><ctag>ign</ctag></lex>
    <lex disamb="1"><base>1341</base><ctag>adj:sg:gen:m3:pos</ctag></lex>
    <ann chan="nam">0</ann>
   </tok>
   <tok>
    <orth>roku</orth>
    <lex disamb="1"><base>rok</base><ctag>subst:sg:gen:m3</ctag></lex>
    <lex><base>rok</base><ctag>subst:sg:loc:m3</ctag></lex>
    <lex><base>rok</base><ctag>subst:sg:voc:m3</ctag></lex>
    <ann chan="nam">0</ann>
   </tok>
   <ns/>
   <tok>
    <orth>,</orth>
    <lex disamb="1"><base>,</base><ctag>interp</ctag></lex>
    <ann chan="nam">0</ann>
   </tok>
   <tok>
    <orth>w</orth>
    <lex><base>w</base><ctag>prep:acc:nwok</ctag></lex>
    <lex disamb="1"><base>w</base><ctag>prep:loc:nwok</ctag></lex>
    <lex><base>wiek</base><ctag>brev:pun</ctag></lex>
    <lex><base>wielki</base><ctag>brev:pun</ctag></lex>
    <lex><base>wiersz</base><ctag>brev:pun</ctag></lex>
    <lex><base>wieś</base><ctag>brev:pun</ctag></lex>
    <lex><base>wyspa</base><ctag>brev:pun</ctag></lex>
    <ann chan="nam">0</ann>
   </tok>
   <tok>
    <orth>okresie</orth>
    <lex disamb="1"><base>okres</base><ctag>subst:sg:loc:m3</ctag></lex>
    <lex><base>okres</base><ctag>subst:sg:voc:m3</ctag></lex>
    <ann chan="nam">0</ann>
   </tok>
   <tok>
    <orth>kampanii</orth>
    <lex disamb="1"><base>Kampania</base><ctag>subst:sg:gen:f</ctag></lex>
    <lex><base>Kampania</base><ctag>subst:sg:dat:f</ctag></lex>
    <lex><base>Kampania</base><ctag>subst:sg:loc:f</ctag></lex>
    <lex><base>Kampania</base><ctag>subst:pl:gen:f</ctag></lex>
    <lex disamb="1"><base>kampania</base><ctag>subst:sg:gen:f</ctag></lex>
    <lex><base>kampania</base><ctag>subst:sg:dat:f</ctag></lex>
    <lex><base>kampania</base><ctag>subst:sg:loc:f</ctag></lex>
    <lex><base>kampania</base><ctag>subst:pl:gen:f</ctag></lex>
    <ann chan="nam">0</ann>
   </tok>
   <tok>
    <orth>ruskiej</orth>
    <lex disamb="1"><base>ruski</base><ctag>adj:sg:gen:f:pos</ctag></lex>
    <lex><base>ruski</base><ctag>adj:sg:dat:f:pos</ctag></lex>
    <lex><base>ruski</base><ctag>adj:sg:loc:f:pos</ctag></lex>
    <ann chan="nam">0</ann>
   </tok>
   <tok>
    <orth>Kazimierza</orth>
    <lex disamb="1"><base>Kazimierz</base><ctag>subst:sg:gen:m1</ctag></lex>
    <lex><base>Kazimierz</base><ctag>subst:sg:acc:m1</ctag></lex>
    <lex><base>Kazimierz</base><ctag>subst:sg:gen:m3</ctag></lex>
    <ann chan="nam">4</ann>
   </tok>
   <tok>
    <orth>Wielkiego</orth>
    <lex disamb="1"><base>wielki</base><ctag>adj:sg:gen:m1:pos</ctag></lex>
    <lex><base>wielki</base><ctag>adj:sg:acc:m1:pos</ctag></lex>
    <lex><base>wielki</base><ctag>adj:sg:gen:m2:pos</ctag></lex>
    <lex><base>wielki</base><ctag>adj:sg:acc:m2:pos</ctag></lex>
    <lex><base>wielki</base><ctag>adj:sg:gen:m3:pos</ctag></lex>
    <lex><base>wielki</base><ctag>adj:sg:gen:n:pos</ctag></lex>
    <lex><base>wielki</base><ctag>subst:sg:gen:m1</ctag></lex>
    <lex><base>wielki</base><ctag>subst:sg:acc:m1</ctag></lex>
    <ann chan="nam">4</ann>
   </tok>
   <tok>
    <orth>z</orth>
    <lex disamb="1"><base>z</base><ctag>prep:gen:nwok</ctag></lex>
    <lex><base>z</base><ctag>prep:acc:nwok</ctag></lex>
    <lex><base>z</base><ctag>prep:inst:nwok</ctag></lex>
    <lex><base>z</base><ctag>qub</ctag></lex>
    <lex><base>zeszyt</base><ctag>brev:pun</ctag></lex>
    <ann chan="nam">0</ann>
   </tok>
   <tok>
    <orth>lat</orth>
    <lex><base>lato</base><ctag>subst:pl:gen:n</ctag></lex>
    <lex disamb="1"><base>rok</base><ctag>subst:pl:gen:m3</ctag></lex>
    <ann chan="nam">0</ann>
   </tok>
   <tok>
    <orth>1340</orth>
    <lex><base>1340</base><ctag>ign</ctag></lex>
    <lex disamb="1"><base>1340</base><ctag>num:pl:nom:m3:rec</ctag></lex>
    <ann chan="nam">0</ann>
   </tok>
   <ns/>
   <tok>
    <orth>-</orth>
    <lex disamb="1"><base>-</base><ctag>interp</ctag></lex>
    <ann chan="nam">0</ann>
   </tok>
   <ns/>
   <tok>
    <orth>1341</orth>
    <lex><base>1341</base><ctag>ign</ctag></lex>
    <lex disamb="1"><base>1341</base><ctag>num:pl:nom:m3:rec</ctag></lex>
    <ann chan="nam">0</ann>
   </tok>
   <ns/>
   <tok>
    <orth>.</orth>
    <lex disamb="1"><base>.</base><ctag>interp</ctag></lex>
    <ann chan="nam">0</ann>
   </tok>
  </sentence>
 </chunk>
 <chunk id="ch3">
  <sentence id="sent3">
   <tok>
    <orth>Przebieg</orth>
    <lex disamb="1"><base>przebieg</base><ctag>subst:sg:nom:m3</ctag></lex>
    <lex><base>przebieg</base><ctag>subst:sg:acc:m3</ctag></lex>
   </tok>
   <tok>
    <orth>bitwy</orth>
    <lex disamb="1"><base>bitwa</base><ctag>subst:sg:gen:f</ctag></lex>
    <lex><base>bitwa</base><ctag>subst:pl:nom:f</ctag></lex>
    <lex><base>bitwa</base><ctag>subst:pl:acc:f</ctag></lex>
    <lex><base>bitwa</base><ctag>subst:pl:voc:f</ctag></lex>
   </tok>
  </sentence>
 </chunk>
 <chunk id="ch4">
  <sentence id="sent4">
   <tok>
    <orth>Kresowe</orth>
    <lex disamb="1"><base>kresowy</base><ctag>adj:sg:nom:n:pos</ctag></lex>
    <lex><base>kresowy</base><ctag>adj:sg:acc:n:pos</ctag></lex>
    <lex><base>kresowy</base><ctag>adj:sg:voc:n:pos</ctag></lex>
    <lex><base>kresowy</base><ctag>adj:pl:nom:m2:pos</ctag></lex>
    <lex><base>kresowy</base><ctag>adj:pl:acc:m2:pos</ctag></lex>
    <lex><base>kresowy</base><ctag>adj:pl:voc:m2:pos</ctag></lex>
    <lex><base>kresowy</base><ctag>adj:pl:nom:m3:pos</ctag></lex>
    <lex><base>kresowy</base><ctag>adj:pl:acc:m3:pos</ctag></lex>
    <lex><base>kresowy</base><ctag>adj:pl:voc:m3:pos</ctag></lex>
    <lex><base>kresowy</base><ctag>adj:pl:nom:f:pos</ctag></lex>
    <lex><base>kresowy</base><ctag>adj:pl:acc:f:pos</ctag></lex>
    <lex><base>kresowy</base><ctag>adj:pl:voc:f:pos</ctag></lex>
    <lex><base>kresowy</base><ctag>adj:pl:nom:n:pos</ctag></lex>
    <lex><base>kresowy</base><ctag>adj:pl:acc:n:pos</ctag></lex>
    <lex><base>kresowy</base><ctag>adj:pl:voc:n:pos</ctag></lex>
    <ann chan="nam">0</ann>
   </tok>
   <tok>
    <orth>położenie</orth>
    <lex disamb="1"><base>położenie</base><ctag>subst:sg:nom:n</ctag></lex>
    <lex><base>położenie</base><ctag>subst:sg:acc:n</ctag></lex>
    <lex><base>położenie</base><ctag>subst:sg:voc:n</ctag></lex>
    <lex><base>położyć</base><ctag>ger:sg:nom:n:perf:aff</ctag></lex>
    <lex><base>położyć</base><ctag>ger:sg:acc:n:perf:aff</ctag></lex>
    <ann chan="nam">0</ann>
   </tok>
   <tok>
    <orth>Lublina</orth>
    <lex disamb="1"><base>Lublin</base><ctag>subst:sg:gen:m3</ctag></lex>
    <lex disamb="1"><base>lublin</base><ctag>subst:sg:gen:m3</ctag></lex>
    <ann chan="nam">1</ann>
   </tok>
   <tok>
    <orth>na</orth>
    <lex><base>na</base><ctag>interj</ctag></lex>
    <lex><base>na</base><ctag>prep:acc</ctag></lex>
    <lex disamb="1"><base>na</base><ctag>prep:loc</ctag></lex>
    <ann chan="nam">0</ann>
   </tok>
   <tok>
    <orth>pograniczu</orth>
    <lex><base>pogranicze</base><ctag>subst:sg:dat:n</ctag></lex>
    <lex disamb="1"><base>pogranicze</base><ctag>subst:sg:loc:n</ctag></lex>
    <ann chan="nam">0</ann>
   </tok>
   <tok>
    <orth>ówczesnego</orth>
    <lex><base>ówczesny</base><ctag>adj:sg:gen:m1:pos</ctag></lex>
    <lex><base>ówczesny</base><ctag>adj:sg:acc:m1:pos</ctag></lex>
    <lex><base>ówczesny</base><ctag>adj:sg:gen:m2:pos</ctag></lex>
    <lex><base>ówczesny</base><ctag>adj:sg:acc:m2:pos</ctag></lex>
    <lex><base>ówczesny</base><ctag>adj:sg:gen:m3:pos</ctag></lex>
    <lex disamb="1"><base>ówczesny</base><ctag>adj:sg:gen:n:pos</ctag></lex>
    <ann chan="nam">0</ann>
   </tok>
   <tok>
    <orth>państwa</orth>
    <lex disamb="1"><base>państwo</base><ctag>subst:sg:gen:n</ctag></lex>
    <lex><base>państwo</base><ctag>subst:pl:gen:m1</ctag></lex>
    <lex><base>państwo</base><ctag>subst:pl:acc:m1</ctag></lex>
    <lex><base>państwo</base><ctag>subst:pl:nom:n</ctag></lex>
    <lex><base>państwo</base><ctag>subst:pl:acc:n</ctag></lex>
    <lex><base>państwo</base><ctag>subst:pl:voc:n</ctag></lex>
    <ann chan="nam">0</ann>
   </tok>
   <tok>
    <orth>powodowało</orth>
    <lex disamb="1"><base>powodować</base><ctag>praet:sg:n:imperf</ctag></lex>
    <ann chan="nam">0</ann>
   </tok>
   <tok>
    <orth>częste</orth>
    <lex><base>częsty</base><ctag>adj:sg:nom:n:pos</ctag></lex>
    <lex><base>częsty</base><ctag>adj:sg:acc:n:pos</ctag></lex>
    <lex><base>częsty</base><ctag>adj:sg:voc:n:pos</ctag></lex>
    <lex><base>częsty</base><ctag>adj:pl:nom:m2:pos</ctag></lex>
    <lex><base>częsty</base><ctag>adj:pl:acc:m2:pos</ctag></lex>
    <lex><base>częsty</base><ctag>adj:pl:voc:m2:pos</ctag></lex>
    <lex><base>częsty</base><ctag>adj:pl:nom:m3:pos</ctag></lex>
    <lex disamb="1"><base>częsty</base><ctag>adj:pl:acc:m3:pos</ctag></lex>
    <lex><base>częsty</base><ctag>adj:pl:voc:m3:pos</ctag></lex>
    <lex><base>częsty</base><ctag>adj:pl:nom:f:pos</ctag></lex>
    <lex><base>częsty</base><ctag>adj:pl:acc:f:pos</ctag></lex>
    <lex><base>częsty</base><ctag>adj:pl:voc:f:pos</ctag></lex>
    <lex><base>częsty</base><ctag>adj:pl:nom:n:pos</ctag></lex>
    <lex><base>częsty</base><ctag>adj:pl:acc:n:pos</ctag></lex>
    <lex><base>częsty</base><ctag>adj:pl:voc:n:pos</ctag></lex>
    <ann chan="nam">0</ann>
   </tok>
   <tok>
    <orth>najazdy</orth>
    <lex><base>najazd</base><ctag>subst:pl:nom:m3</ctag></lex>
    <lex disamb="1"><base>najazd</base><ctag>subst:pl:acc:m3</ctag></lex>
    <lex><base>najazd</base><ctag>subst:pl:voc:m3</ctag></lex>
    <ann chan="nam">0</ann>
   </tok>
   <tok>
    <orth>Litwinów</orth>
    <lex disamb="1"><base>Litwin</base><ctag>subst:pl:gen:m1</ctag></lex>
    <lex><base>Litwin</base><ctag>subst:pl:acc:m1</ctag></lex>
    <ann chan="nam">2</ann>
   </tok>
   <ns/>
   <tok>
    <orth>,</orth>
    <lex disamb="1"><base>,</base><ctag>interp</ctag></lex>
    <ann chan="nam">0</ann>
   </tok>
   <tok>
    <orth>Jaćwingów</orth>
    <lex><base>Jaćwingów</base><ctag>ign</ctag></lex>
    <lex disamb="1"><base>jaćwingów</base><ctag>subst:sg:nom:m1</ctag></lex>
    <ann chan="nam">3</ann>
   </tok>
   <ns/>
   <tok>
    <orth>,</orth>
    <lex disamb="1"><base>,</base><ctag>interp</ctag></lex>
    <ann chan="nam">0</ann>
   </tok>
   <tok>
    <orth>Rusinów</orth>
    <lex><base>Rusin</base><ctag>subst:pl:gen:m1</ctag></lex>
    <lex><base>Rusin</base><ctag>subst:pl:acc:m1</ctag></lex>
    <lex disamb="1"><base>Rusinów</base><ctag>subst:sg:nom:m3</ctag></lex>
    <lex><base>Rusinów</base><ctag>subst:sg:acc:m3</ctag></lex>
    <ann chan="nam">4</ann>
   </tok>
   <tok>
    <orth>i</orth>
    <lex disamb="1"><base>i</base><ctag>conj</ctag></lex>
    <lex><base>i</base><ctag>interj</ctag></lex>
    <lex><base>i</base><ctag>qub</ctag></lex>
    <ann chan="nam">0</ann>
   </tok>
   <tok>
    <orth>Tatarów</orth>
    <lex disamb="1"><base>Tatar</base><ctag>subst:pl:gen:m1</ctag></lex>
    <lex><base>Tatar</base><ctag>subst:pl:acc:m1</ctag></lex>
    <lex><base>tatar</base><ctag>subst:pl:gen:m2</ctag></lex>
    <lex><base>tatar</base><ctag>subst:pl:gen:m3</ctag></lex>
    <ann chan="nam">5</ann>
   </tok>
   <ns/>
   <tok>
    <orth>.</orth>
    <lex disamb="1"><base>.</base><ctag>interp</ctag></lex>
    <ann chan="nam">0</ann>
   </tok>
  </sentence>
  <sentence id="sent5">
   <tok>
    <orth>Na</orth>
    <lex><base>na</base><ctag>interj</ctag></lex>
    <lex><base>na</base><ctag>prep:acc</ctag></lex>
    <lex disamb="1"><base>na</base><ctag>prep:loc</ctag></lex>
    <ann chan="nam">0</ann>
   </tok>
   <tok>
    <orth>przełomie</orth>
    <lex disamb="1"><base>przełom</base><ctag>subst:sg:loc:m3</ctag></lex>
    <lex><base>przełom</base><ctag>subst:sg:voc:m3</ctag></lex>
    <ann chan="nam">0</ann>
   </tok>
   <tok>
    <orth>stycznia</orth>
    <lex disamb="1"><base>styczeń</base><ctag>subst:sg:gen:m3</ctag></lex>
    <ann chan="nam">0</ann>
   </tok>
   <tok>
    <orth>i</orth>
    <lex disamb="1"><base>i</base><ctag>conj</ctag></lex>
    <lex><base>i</base><ctag>interj</ctag></lex>
    <lex><base>i</base><ctag>qub</ctag></lex>
    <ann chan="nam">0</ann>
   </tok>
   <tok>
    <orth>lutego</orth>
    <lex><base>luty</base><ctag>adj:sg:gen:m1:pos</ctag></lex>
    <lex><base>luty</base><ctag>adj:sg:acc:m1:pos</ctag></lex>
    <lex><base>luty</base><ctag>adj:sg:gen:m2:pos</ctag></lex>
    <lex><base>luty</base><ctag>adj:sg:acc:m2:pos</ctag></lex>
    <lex><base>luty</base><ctag>adj:sg:gen:m3:pos</ctag></lex>
    <lex><base>luty</base><ctag>adj:sg:gen:n:pos</ctag></lex>
    <lex disamb="1"><base>luty</base><ctag>subst:sg:gen:m3</ctag></lex>
    <ann chan="nam">0</ann>
   </tok>
   <tok>
    <orth>1341</orth>
    <lex><base>1341</base><ctag>ign</ctag></lex>
    <lex disamb="1"><base>1341</base><ctag>adj:sg:gen:m3:pos</ctag></lex>
    <ann chan="nam">0</ann>
   </tok>
   <tok>
    <orth>roku</orth>
    <lex disamb="1"><base>rok</base><ctag>subst:sg:gen:m3</ctag></lex>
    <lex><base>rok</base><ctag>subst:sg:loc:m3</ctag></lex>
    <lex><base>rok</base><ctag>subst:sg:voc:m3</ctag></lex>
    <ann chan="nam">0</ann>
   </tok>
   <ns/>
   <tok>
    <orth>,</orth>
    <lex disamb="1"><base>,</base><ctag>interp</ctag></lex>
    <ann chan="nam">0</ann>
   </tok>
   <tok>
    <orth>po</orth>
    <lex><base>PO</base><ctag>subst:sg:nom:f</ctag></lex>
    <lex><base>PO</base><ctag>subst:sg:gen:f</ctag></lex>
    <lex><base>PO</base><ctag>subst:sg:dat:f</ctag></lex>
    <lex><base>PO</base><ctag>subst:sg:acc:f</ctag></lex>
    <lex><base>PO</base><ctag>subst:sg:inst:f</ctag></lex>
    <lex><base>PO</base><ctag>subst:sg:loc:f</ctag></lex>
    <lex><base>PO</base><ctag>subst:sg:voc:f</ctag></lex>
    <lex><base>PO</base><ctag>subst:sg:nom:n</ctag></lex>
    <lex><base>PO</base><ctag>subst:sg:gen:n</ctag></lex>
    <lex><base>PO</base><ctag>subst:sg:dat:n</ctag></lex>
    <lex><base>PO</base><ctag>subst:sg:acc:n</ctag></lex>
    <lex><base>PO</base><ctag>subst:sg:inst:n</ctag></lex>
    <lex><base>PO</base><ctag>subst:sg:loc:n</ctag></lex>
    <lex><base>PO</base><ctag>subst:sg:voc:n</ctag></lex>
    <lex><base>PO</base><ctag>subst:pl:nom:f</ctag></lex>
    <lex><base>PO</base><ctag>subst:pl:gen:f</ctag></lex>
    <lex><base>PO</base><ctag>subst:pl:dat:f</ctag></lex>
    <lex><base>PO</base><ctag>subst:pl:acc:f</ctag></lex>
    <lex><base>PO</base><ctag>subst:pl:inst:f</ctag></lex>
    <lex><base>PO</base><ctag>subst:pl:loc:f</ctag></lex>
    <lex><base>PO</base><ctag>subst:pl:voc:f</ctag></lex>
    <lex><base>PO</base><ctag>subst:pl:nom:n</ctag></lex>
    <lex><base>PO</base><ctag>subst:pl:gen:n</ctag></lex>
    <lex><base>PO</base><ctag>subst:pl:dat:n</ctag></lex>
    <lex><base>PO</base><ctag>subst:pl:acc:n</ctag></lex>
    <lex><base>PO</base><ctag>subst:pl:inst:n</ctag></lex>
    <lex><base>PO</base><ctag>subst:pl:loc:n</ctag></lex>
    <lex><base>PO</base><ctag>subst:pl:voc:n</ctag></lex>
    <lex><base>po</base><ctag>prep:acc</ctag></lex>
    <lex disamb="1"><base>po</base><ctag>prep:loc</ctag></lex>
    <ann chan="nam">0</ann>
   </tok>
   <tok>
    <orth>nieudanej</orth>
    <lex><base>nieudany</base><ctag>adj:sg:gen:f:pos</ctag></lex>
    <lex><base>nieudany</base><ctag>adj:sg:dat:f:pos</ctag></lex>
    <lex disamb="1"><base>nieudany</base><ctag>adj:sg:loc:f:pos</ctag></lex>
    <lex><base>udać</base><ctag>ppas:sg:gen:f:perf:neg</ctag></lex>
    <lex><base>udać</base><ctag>ppas:sg:dat:f:perf:neg</ctag></lex>
    <lex><base>udać</base><ctag>ppas:sg:loc:f:perf:neg</ctag></lex>
    <ann chan="nam">0</ann>
   </tok>
   <tok>
    <orth>próbie</orth>
    <lex><base>próba</base><ctag>subst:sg:dat:f</ctag></lex>
    <lex disamb="1"><base>próba</base><ctag>subst:sg:loc:f</ctag></lex>
    <ann chan="nam">0</ann>
   </tok>
   <tok>
    <orth>sforsowania</orth>
    <lex disamb="1"><base>sforsować</base><ctag>ger:sg:gen:n:perf:aff</ctag></lex>
    <ann chan="nam">0</ann>
   </tok>
   <tok>
    <orth>Wisły</orth>
    <lex disamb="1"><base>Wisła</base><ctag>subst:sg:gen:f</ctag></lex>
    <lex><base>Wisła</base><ctag>subst:pl:nom:f</ctag></lex>
    <lex><base>Wisła</base><ctag>subst:pl:acc:f</ctag></lex>
    <lex><base>Wisła</base><ctag>subst:pl:voc:f</ctag></lex>
    <ann chan="nam">1</ann>
   </tok>
   <tok>
    <orth>siły</orth>
    <lex disamb="1"><base>siła</base><ctag>subst:sg:gen:f</ctag></lex>
    <lex><base>siła</base><ctag>subst:pl:nom:f</ctag></lex>
    <lex><base>siła</base><ctag>subst:pl:acc:f</ctag></lex>
    <lex><base>siła</base><ctag>subst:pl:voc:f</ctag></lex>
    <lex><base>siły</base><ctag>subst:pl:nom:n</ctag></lex>
    <lex><base>siły</base><ctag>subst:pl:acc:n</ctag></lex>
    <lex><base>siły</base><ctag>subst:pl:voc:n</ctag></lex>
    <ann chan="nam">0</ann>
   </tok>
   <tok>
    <orth>tatarskie</orth>
    <lex disamb="1"><base>tatarski</base><ctag>adj:sg:nom:n:pos</ctag></lex>
    <lex><base>tatarski</base><ctag>adj:sg:acc:n:pos</ctag></lex>
    <lex><base>tatarski</base><ctag>adj:sg:voc:n:pos</ctag></lex>
    <lex><base>tatarski</base><ctag>adj:pl:nom:m2:pos</ctag></lex>
    <lex><base>tatarski</base><ctag>adj:pl:acc:m2:pos</ctag></lex>
    <lex><base>tatarski</base><ctag>adj:pl:voc:m2:pos</ctag></lex>
    <lex><base>tatarski</base><ctag>adj:pl:nom:m3:pos</ctag></lex>
    <lex><base>tatarski</base><ctag>adj:pl:acc:m3:pos</ctag></lex>
    <lex><base>tatarski</base><ctag>adj:pl:voc:m3:pos</ctag></lex>
    <lex><base>tatarski</base><ctag>adj:pl:nom:f:pos</ctag></lex>
    <lex><base>tatarski</base><ctag>adj:pl:acc:f:pos</ctag></lex>
    <lex><base>tatarski</base><ctag>adj:pl:voc:f:pos</ctag></lex>
    <lex><base>tatarski</base><ctag>adj:pl:nom:n:pos</ctag></lex>
    <lex><base>tatarski</base><ctag>adj:pl:acc:n:pos</ctag></lex>
    <lex><base>tatarski</base><ctag>adj:pl:voc:n:pos</ctag></lex>
    <ann chan="nam">2</ann>
   </tok>
   <tok>
    <orth>wraz</orth>
    <lex disamb="1"><base>wraz</base><ctag>burk</ctag></lex>
    <lex><base>wraz</base><ctag>subst:sg:nom:m3</ctag></lex>
    <lex><base>wraz</base><ctag>subst:sg:acc:m3</ctag></lex>
    <ann chan="nam">0</ann>
   </tok>
   <tok>
    <orth>z</orth>
    <lex><base>z</base><ctag>prep:gen:nwok</ctag></lex>
    <lex><base>z</base><ctag>prep:acc:nwok</ctag></lex>
    <lex disamb="1"><base>z</base><ctag>prep:inst:nwok</ctag></lex>
    <lex><base>z</base><ctag>qub</ctag></lex>
    <lex><base>zeszyt</base><ctag>brev:pun</ctag></lex>
    <ann chan="nam">0</ann>
   </tok>
   <tok>
    <orth>posiłkami</orth>
    <lex disamb="1"><base>posiłek</base><ctag>subst:pl:inst:m3</ctag></lex>
    <lex><base>posiłki</base><ctag>subst:pl:inst:n</ctag></lex>
    <ann chan="nam">0</ann>
   </tok>
   <tok>
    <orth>ruskimi</orth>
    <lex><base>Ruski</base><ctag>subst:pl:inst:m1</ctag></lex>
    <lex><base>ruski</base><ctag>adj:pl:inst:m1:pos</ctag></lex>
    <lex><base>ruski</base><ctag>adj:pl:inst:m2:pos</ctag></lex>
    <lex disamb="1"><base>ruski</base><ctag>adj:pl:inst:m3:pos</ctag></lex>
    <lex><base>ruski</base><ctag>adj:pl:inst:f:pos</ctag></lex>
    <lex><base>ruski</base><ctag>adj:pl:inst:n:pos</ctag></lex>
    <lex><base>ruski</base><ctag>subst:pl:inst:m3</ctag></lex>
    <lex><base>ruskie</base><ctag>subst:pl:inst:n</ctag></lex>
    <ann chan="nam">0</ann>
   </tok>
   <ns/>
   <tok>
    <orth>,</orth>
    <lex disamb="1"><base>,</base><ctag>interp</ctag></lex>
    <ann chan="nam">0</ann>
   </tok>
   <tok>
    <orth>które</orth>
    <lex><base>który</base><ctag>adj:sg:nom:n:pos</ctag></lex>
    <lex><base>który</base><ctag>adj:sg:acc:n:pos</ctag></lex>
    <lex><base>który</base><ctag>adj:sg:voc:n:pos</ctag></lex>
    <lex><base>który</base><ctag>adj:pl:nom:m2:pos</ctag></lex>
    <lex><base>który</base><ctag>adj:pl:acc:m2:pos</ctag></lex>
    <lex><base>który</base><ctag>adj:pl:voc:m2:pos</ctag></lex>
    <lex><base>który</base><ctag>adj:pl:nom:m3:pos</ctag></lex>
    <lex><base>który</base><ctag>adj:pl:acc:m3:pos</ctag></lex>
    <lex><base>który</base><ctag>adj:pl:voc:m3:pos</ctag></lex>
    <lex><base>który</base><ctag>adj:pl:nom:f:pos</ctag></lex>
    <lex disamb="1"><base>który</base><ctag>adj:pl:acc:f:pos</ctag></lex>
    <lex><base>który</base><ctag>adj:pl:voc:f:pos</ctag></lex>
    <lex><base>który</base><ctag>adj:pl:nom:n:pos</ctag></lex>
    <lex><base>który</base><ctag>adj:pl:acc:n:pos</ctag></lex>
    <lex><base>który</base><ctag>adj:pl:voc:n:pos</ctag></lex>
    <ann chan="nam">0</ann>
   </tok>
   <tok>
    <orth>prowadził</orth>
    <lex disamb="1"><base>prowadzić</base><ctag>praet:sg:m1:imperf</ctag></lex>
    <lex><base>prowadzić</base><ctag>praet:sg:m2:imperf</ctag></lex>
    <lex><base>prowadzić</base><ctag>praet:sg:m3:imperf</ctag></lex>
    <ann chan="nam">0</ann>
   </tok>
   <tok>
    <orth>Dymitr</orth>
    <lex disamb="1"><base>Dymitr</base><ctag>subst:sg:nom:m1</ctag></lex>
    <ann chan="nam">3</ann>
   </tok>
   <tok>
    <orth>Detko</orth>
    <lex><base>Detko</base><ctag>ign</ctag></lex>
    <lex disamb="1"><base>detko</base><ctag>subst:sg:nom:m1</ctag></lex>
    <ann chan="nam">3</ann>
   </tok>
   <tok>
    <orth>wycofały</orth>
    <lex><base>wycofać</base><ctag>praet:pl:m2:perf</ctag></lex>
    <lex disamb="1"><base>wycofać</base><ctag>praet:pl:m3:perf</ctag></lex>
    <lex><base>wycofać</base><ctag>praet:pl:f:perf</ctag></lex>
    <lex><base>wycofać</base><ctag>praet:pl:n:perf</ctag></lex>
    <ann chan="nam">0</ann>
   </tok>
   <tok>
    <orth>się</orth>
    <lex disamb="1"><base>się</base><ctag>qub</ctag></lex>
    <ann chan="nam">0</ann>
   </tok>
   <tok>
    <orth>w</orth>
    <lex><base>w</base><ctag>prep:acc:nwok</ctag></lex>
    <lex disamb="1"><base>w</base><ctag>prep:loc:nwok</ctag></lex>
    <lex><base>wiek</base><ctag>brev:pun</ctag></lex>
    <lex><base>wielki</base><ctag>brev:pun</ctag></lex>
    <lex><base>wiersz</base><ctag>brev:pun</ctag></lex>
    <lex><base>wieś</base><ctag>brev:pun</ctag></lex>
    <lex><base>wyspa</base><ctag>brev:pun</ctag></lex>
    <ann chan="nam">0</ann>
   </tok>
   <tok>
    <orth>kierunku</orth>
    <lex><base>kierunek</base><ctag>subst:sg:gen:m3</ctag></lex>
    <lex disamb="1"><base>kierunek</base><ctag>subst:sg:loc:m3</ctag></lex>
    <lex><base>kierunek</base><ctag>subst:sg:voc:m3</ctag></lex>
    <ann chan="nam">0</ann>
   </tok>
   <tok>
    <orth>Lublina</orth>
    <lex disamb="1"><base>Lublin</base><ctag>subst:sg:gen:m3</ctag></lex>
    <lex disamb="1"><base>lublin</base><ctag>subst:sg:gen:m3</ctag></lex>
    <ann chan="nam">4</ann>
   </tok>
   <ns/>
   <tok>
    <orth>.</orth>
    <lex disamb="1"><base>.</base><ctag>interp</ctag></lex>
    <ann chan="nam">0</ann>
   </tok>
  </sentence>
  <sentence id="sent6">
   <tok>
    <orth>Najeźdźcy</orth>
    <lex><base>najeźdźca</base><ctag>subst:sg:gen:m1</ctag></lex>
    <lex><base>najeźdźca</base><ctag>subst:sg:dat:m1</ctag></lex>
    <lex><base>najeźdźca</base><ctag>subst:sg:loc:m1</ctag></lex>
    <lex disamb="1"><base>najeźdźca</base><ctag>subst:pl:nom:m1</ctag></lex>
    <lex><base>najeźdźca</base><ctag>subst:pl:voc:m1</ctag></lex>
    <ann chan="nam">0</ann>
   </tok>
   <tok>
    <orth>rozlali</orth>
    <lex disamb="1"><base>rozlać</base><ctag>praet:pl:m1:perf</ctag></lex>
    <ann chan="nam">0</ann>
   </tok>
   <tok>
    <orth>się</orth>
    <lex disamb="1"><base>się</base><ctag>qub</ctag></lex>
    <ann chan="nam">0</ann>
   </tok>
   <tok>
    <orth>po</orth>
    <lex><base>PO</base><ctag>subst:sg:nom:f</ctag></lex>
    <lex><base>PO</base><ctag>subst:sg:gen:f</ctag></lex>
    <lex><base>PO</base><ctag>subst:sg:dat:f</ctag></lex>
    <lex><base>PO</base><ctag>subst:sg:acc:f</ctag></lex>
    <lex><base>PO</base><ctag>subst:sg:inst:f</ctag></lex>
    <lex><base>PO</base><ctag>subst:sg:loc:f</ctag></lex>
    <lex><base>PO</base><ctag>subst:sg:voc:f</ctag></lex>
    <lex><base>PO</base><ctag>subst:sg:nom:n</ctag></lex>
    <lex><base>PO</base><ctag>subst:sg:gen:n</ctag></lex>
    <lex><base>PO</base><ctag>subst:sg:dat:n</ctag></lex>
    <lex><base>PO</base><ctag>subst:sg:acc:n</ctag></lex>
    <lex><base>PO</base><ctag>subst:sg:inst:n</ctag></lex>
    <lex><base>PO</base><ctag>subst:sg:loc:n</ctag></lex>
    <lex><base>PO</base><ctag>subst:sg:voc:n</ctag></lex>
    <lex><base>PO</base><ctag>subst:pl:nom:f</ctag></lex>
    <lex><base>PO</base><ctag>subst:pl:gen:f</ctag></lex>
    <lex><base>PO</base><ctag>subst:pl:dat:f</ctag></lex>
    <lex><base>PO</base><ctag>subst:pl:acc:f</ctag></lex>
    <lex><base>PO</base><ctag>subst:pl:inst:f</ctag></lex>
    <lex><base>PO</base><ctag>subst:pl:loc:f</ctag></lex>
    <lex><base>PO</base><ctag>subst:pl:voc:f</ctag></lex>
    <lex><base>PO</base><ctag>subst:pl:nom:n</ctag></lex>
    <lex><base>PO</base><ctag>subst:pl:gen:n</ctag></lex>
    <lex><base>PO</base><ctag>subst:pl:dat:n</ctag></lex>
    <lex><base>PO</base><ctag>subst:pl:acc:n</ctag></lex>
    <lex><base>PO</base><ctag>subst:pl:inst:n</ctag></lex>
    <lex><base>PO</base><ctag>subst:pl:loc:n</ctag></lex>
    <lex><base>PO</base><ctag>subst:pl:voc:n</ctag></lex>
    <lex><base>po</base><ctag>prep:acc</ctag></lex>
    <lex disamb="1"><base>po</base><ctag>prep:loc</ctag></lex>
    <ann chan="nam">0</ann>
   </tok>
   <tok>
    <orth>ziemi</orth>
    <lex><base>Ziemia</base><ctag>subst:sg:gen:f</ctag></lex>
    <lex><base>Ziemia</base><ctag>subst:sg:dat:f</ctag></lex>
    <lex disamb="1"><base>Ziemia</base><ctag>subst:sg:loc:f</ctag></lex>
    <lex><base>ziemia</base><ctag>subst:sg:gen:f</ctag></lex>
    <lex><base>ziemia</base><ctag>subst:sg:dat:f</ctag></lex>
    <lex disamb="1"><base>ziemia</base><ctag>subst:sg:loc:f</ctag></lex>
    <ann chan="nam">1</ann>
   </tok>
   <tok>
    <orth>lubelskiej</orth>
    <lex><base>lubelski</base><ctag>adj:sg:gen:f:pos</ctag></lex>
    <lex><base>lubelski</base><ctag>adj:sg:dat:f:pos</ctag></lex>
    <lex disamb="1"><base>lubelski</base><ctag>adj:sg:loc:f:pos</ctag></lex>
    <ann chan="nam">1</ann>
   </tok>
   <tok>
    <orth>grabiąc</orth>
    <lex disamb="1"><base>grabić</base><ctag>pcon:imperf</ctag></lex>
    <ann chan="nam">0</ann>
   </tok>
   <tok>
    <orth>i</orth>
    <lex disamb="1"><base>i</base><ctag>conj</ctag></lex>
    <lex><base>i</base><ctag>interj</ctag></lex>
    <lex><base>i</base><ctag>qub</ctag></lex>
    <ann chan="nam">0</ann>
   </tok>
   <tok>
    <orth>mordując</orth>
    <lex disamb="1"><base>mordować</base><ctag>pcon:imperf</ctag></lex>
    <ann chan="nam">0</ann>
   </tok>
   <ns/>
   <tok>
    <orth>.</orth>
    <lex disamb="1"><base>.</base><ctag>interp</ctag></lex>
    <ann chan="nam">0</ann>
   </tok>
  </sentence>
  <sentence id="sent7">
   <tok>
    <orth>Oblegli</orth>
    <lex disamb="1"><base>oblec</base><ctag>praet:pl:m1:perf</ctag></lex>
    <lex><base>obległy</base><ctag>adj:pl:nom:m1:pos</ctag></lex>
    <lex><base>obległy</base><ctag>adj:pl:voc:m1:pos</ctag></lex>
    <ann chan="nam">0</ann>
   </tok>
   <tok>
    <orth>także</orth>
    <lex disamb="1"><base>także</base><ctag>qub</ctag></lex>
    <ann chan="nam">0</ann>
   </tok>
   <tok>
    <orth>gród</orth>
    <lex><base>gród</base><ctag>subst:sg:nom:m3</ctag></lex>
    <lex disamb="1"><base>gród</base><ctag>subst:sg:acc:m3</ctag></lex>
    <ann chan="nam">0</ann>
   </tok>
   <tok>
    <orth>lubelski</orth>
    <lex><base>lubelski</base><ctag>adj:sg:nom:m1:pos</ctag></lex>
    <lex><base>lubelski</base><ctag>adj:sg:voc:m1:pos</ctag></lex>
    <lex><base>lubelski</base><ctag>adj:sg:nom:m2:pos</ctag></lex>
    <lex><base>lubelski</base><ctag>adj:sg:voc:m2:pos</ctag></lex>
    <lex><base>lubelski</base><ctag>adj:sg:nom:m3:pos</ctag></lex>
    <lex disamb="1"><base>lubelski</base><ctag>adj:sg:acc:m3:pos</ctag></lex>
    <lex><base>lubelski</base><ctag>adj:sg:voc:m3:pos</ctag></lex>
    <ann chan="nam">1</ann>
   </tok>
   <tok>
    <orth>i</orth>
    <lex disamb="1"><base>i</base><ctag>conj</ctag></lex>
    <lex><base>i</base><ctag>interj</ctag></lex>
    <lex><base>i</base><ctag>qub</ctag></lex>
    <ann chan="nam">0</ann>
   </tok>
   <tok>
    <orth>puścili</orth>
    <lex disamb="1"><base>puścić</base><ctag>praet:pl:m1:perf</ctag></lex>
    <ann chan="nam">0</ann>
   </tok>
   <tok>
    <orth>z</orth>
    <lex><base>z</base><ctag>prep:gen:nwok</ctag></lex>
    <lex><base>z</base><ctag>prep:acc:nwok</ctag></lex>
    <lex disamb="1"><base>z</base><ctag>prep:inst:nwok</ctag></lex>
    <lex><base>z</base><ctag>qub</ctag></lex>
    <lex><base>zeszyt</base><ctag>brev:pun</ctag></lex>
    <ann chan="nam">0</ann>
   </tok>
   <tok>
    <orth>dymem</orth>
    <lex disamb="1"><base>dym</base><ctag>subst:sg:inst:m3</ctag></lex>
    <ann chan="nam">0</ann>
   </tok>
   <tok>
    <orth>stojące</orth>
    <lex><base>stać</base><ctag>pact:sg:nom:n:imperf:aff</ctag></lex>
    <lex><base>stać</base><ctag>pact:sg:acc:n:imperf:aff</ctag></lex>
    <lex><base>stać</base><ctag>pact:pl:nom:m2:imperf:aff</ctag></lex>
    <lex><base>stać</base><ctag>pact:pl:acc:m2:imperf:aff</ctag></lex>
    <lex disamb="1"><base>stać</base><ctag>pact:pl:nom:m3:imperf:aff</ctag></lex>
    <lex><base>stać</base><ctag>pact:pl:acc:m3:imperf:aff</ctag></lex>
    <lex><base>stać</base><ctag>pact:pl:nom:f:imperf:aff</ctag></lex>
    <lex><base>stać</base><ctag>pact:pl:acc:f:imperf:aff</ctag></lex>
    <lex><base>stać</base><ctag>pact:pl:nom:n:imperf:aff</ctag></lex>
    <lex><base>stać</base><ctag>pact:pl:acc:n:imperf:aff</ctag></lex>
    <lex><base>stojąca</base><ctag>subst:pl:nom:f</ctag></lex>
    <lex><base>stojąca</base><ctag>subst:pl:acc:f</ctag></lex>
    <lex><base>stojąca</base><ctag>subst:pl:voc:f</ctag></lex>
    <lex><base>stojący</base><ctag>adj:sg:nom:n:pos</ctag></lex>
    <lex><base>stojący</base><ctag>adj:sg:acc:n:pos</ctag></lex>
    <lex><base>stojący</base><ctag>adj:sg:voc:n:pos</ctag></lex>
    <lex><base>stojący</base><ctag>adj:pl:nom:m2:pos</ctag></lex>
    <lex><base>stojący</base><ctag>adj:pl:acc:m2:pos</ctag></lex>
    <lex><base>stojący</base><ctag>adj:pl:voc:m2:pos</ctag></lex>
    <lex><base>stojący</base><ctag>adj:pl:nom:m3:pos</ctag></lex>
    <lex><base>stojący</base><ctag>adj:pl:acc:m3:pos</ctag></lex>
    <lex><base>stojący</base><ctag>adj:pl:voc:m3:pos</ctag></lex>
    <lex><base>stojący</base><ctag>adj:pl:nom:f:pos</ctag></lex>
    <lex><base>stojący</base><ctag>adj:pl:acc:f:pos</ctag></lex>
    <lex><base>stojący</base><ctag>adj:pl:voc:f:pos</ctag></lex>
    <lex><base>stojący</base><ctag>adj:pl:nom:n:pos</ctag></lex>
    <lex><base>stojący</base><ctag>adj:pl:acc:n:pos</ctag></lex>
    <lex><base>stojący</base><ctag>adj:pl:voc:n:pos</ctag></lex>
    <lex><base>stojący</base><ctag>depr:pl:nom:m2</ctag></lex>
    <lex><base>stojący</base><ctag>depr:pl:voc:m2</ctag></lex>
    <ann chan="nam">0</ann>
   </tok>
   <tok>
    <orth>obok</orth>
    <lex><base>obok</base><ctag>adv</ctag></lex>
    <lex disamb="1"><base>obok</base><ctag>prep:gen</ctag></lex>
    <ann chan="nam">0</ann>
   </tok>
   <tok>
    <orth>niego</orth>
    <lex disamb="1"><base>on</base><ctag>ppron3:sg:gen:m1:ter:akc:praep</ctag></lex>
    <lex><base>on</base><ctag>ppron3:sg:acc:m1:ter:akc:praep</ctag></lex>
    <lex><base>on</base><ctag>ppron3:sg:gen:m2:ter:akc:praep</ctag></lex>
    <lex><base>on</base><ctag>ppron3:sg:acc:m2:ter:akc:praep</ctag></lex>
    <lex><base>on</base><ctag>ppron3:sg:gen:m3:ter:akc:praep</ctag></lex>
    <lex><base>on</base><ctag>ppron3:sg:acc:m3:ter:akc:praep</ctag></lex>
    <lex><base>on</base><ctag>ppron3:sg:gen:n:ter:akc:praep</ctag></lex>
    <ann chan="nam">0</ann>
   </tok>
   <ns/>
   <tok>
    <orth>,</orth>
    <lex disamb="1"><base>,</base><ctag>interp</ctag></lex>
    <ann chan="nam">0</ann>
   </tok>
   <tok>
    <orth>nie</orth>
    <lex><base>nie</base><ctag>conj</ctag></lex>
    <lex disamb="1"><base>nie</base><ctag>qub</ctag></lex>
    <lex><base>on</base><ctag>ppron3:sg:acc:n:ter:akc:praep</ctag></lex>
    <lex><base>on</base><ctag>ppron3:sg:acc:n:ter:nakc:praep</ctag></lex>
    <lex><base>on</base><ctag>ppron3:pl:acc:m2:ter:akc:praep</ctag></lex>
    <lex><base>on</base><ctag>ppron3:pl:acc:m2:ter:nakc:praep</ctag></lex>
    <lex><base>on</base><ctag>ppron3:pl:acc:m3:ter:akc:praep</ctag></lex>
    <lex><base>on</base><ctag>ppron3:pl:acc:m3:ter:nakc:praep</ctag></lex>
    <lex><base>on</base><ctag>ppron3:pl:acc:f:ter:akc:praep</ctag></lex>
    <lex><base>on</base><ctag>ppron3:pl:acc:f:ter:nakc:praep</ctag></lex>
    <lex><base>on</base><ctag>ppron3:pl:acc:n:ter:akc:praep</ctag></lex>
    <lex><base>on</base><ctag>ppron3:pl:acc:n:ter:nakc:praep</ctag></lex>
    <ann chan="nam">0</ann>
   </tok>
   <tok>
    <orth>ufortyfikowane</orth>
    <lex disamb="1"><base>ufortyfikować</base><ctag>ppas:sg:nom:n:perf:aff</ctag></lex>
    <lex><base>ufortyfikować</base><ctag>ppas:sg:acc:n:perf:aff</ctag></lex>
    <lex><base>ufortyfikować</base><ctag>ppas:pl:nom:m2:perf:aff</ctag></lex>
    <lex><base>ufortyfikować</base><ctag>ppas:pl:acc:m2:perf:aff</ctag></lex>
    <lex><base>ufortyfikować</base><ctag>ppas:pl:nom:m3:perf:aff</ctag></lex>
    <lex><base>ufortyfikować</base><ctag>ppas:pl:acc:m3:perf:aff</ctag></lex>
    <lex><base>ufortyfikować</base><ctag>ppas:pl:nom:f:perf:aff</ctag></lex>
    <lex><base>ufortyfikować</base><ctag>ppas:pl:acc:f:perf:aff</ctag></lex>
    <lex><base>ufortyfikować</base><ctag>ppas:pl:nom:n:perf:aff</ctag></lex>
    <lex><base>ufortyfikować</base><ctag>ppas:pl:acc:n:perf:aff</ctag></lex>
    <ann chan="nam">0</ann>
   </tok>
   <tok>
    <orth>miasto</orth>
    <lex><base>miasto</base><ctag>conj</ctag></lex>
    <lex><base>miasto</base><ctag>prep:gen</ctag></lex>
    <lex disamb="1"><base>miasto</base><ctag>subst:sg:nom:n</ctag></lex>
    <lex><base>miasto</base><ctag>subst:sg:acc:n</ctag></lex>
    <lex><base>miasto</base><ctag>subst:sg:voc:n</ctag></lex>
    <ann chan="nam">0</ann>
   </tok>
   <ns/>
   <tok>
    <orth>.</orth>
    <lex disamb="1"><base>.</base><ctag>interp</ctag></lex>
    <ann chan="nam">0</ann>
   </tok>
  </sentence>
  <sentence id="sent8">
   <tok>
    <orth>Pomimo</orth>
    <lex disamb="1"><base>pomimo</base><ctag>prep:gen</ctag></lex>
   </tok>
   <ns/>
   <tok>
    <orth>,</orth>
    <lex disamb="1"><base>,</base><ctag>interp</ctag></lex>
   </tok>
   <tok>
    <orth>ze</orth>
    <lex disamb="1"><base>z</base><ctag>prep:gen:wok</ctag></lex>
    <lex><base>z</base><ctag>prep:acc:wok</ctag></lex>
    <lex><base>z</base><ctag>prep:inst:wok</ctag></lex>
   </tok>
   <tok>
    <orth>gród</orth>
    <lex><base>gród</base><ctag>subst:sg:nom:m3</ctag></lex>
    <lex disamb="1"><base>gród</base><ctag>subst:sg:acc:m3</ctag></lex>
   </tok>
   <tok>
    <orth>miał</orth>
    <lex><base>miał</base><ctag>subst:sg:nom:m3</ctag></lex>
    <lex><base>miał</base><ctag>subst:sg:acc:m3</ctag></lex>
    <lex disamb="1"><base>mieć</base><ctag>praet:sg:m1:imperf</ctag></lex>
    <lex><base>mieć</base><ctag>praet:sg:m2:imperf</ctag></lex>
    <lex><base>mieć</base><ctag>praet:sg:m3:imperf</ctag></lex>
   </tok>
   <tok>
    <orth>wówczas</orth>
    <lex disamb="1"><base>wówczas</base><ctag>adv</ctag></lex>
   </tok>
   <tok>
    <orth>tylko</orth>
    <lex><base>Tylka</base><ctag>subst:sg:voc:f</ctag></lex>
    <lex><base>tylko</base><ctag>conj</ctag></lex>
    <lex disamb="1"><base>tylko</base><ctag>qub</ctag></lex>
   </tok>
   <tok>
    <orth>drewniane</orth>
    <lex><base>drewniany</base><ctag>adj:sg:nom:n:pos</ctag></lex>
    <lex><base>drewniany</base><ctag>adj:sg:acc:n:pos</ctag></lex>
    <lex><base>drewniany</base><ctag>adj:sg:voc:n:pos</ctag></lex>
    <lex><base>drewniany</base><ctag>adj:pl:nom:m2:pos</ctag></lex>
    <lex><base>drewniany</base><ctag>adj:pl:acc:m2:pos</ctag></lex>
    <lex><base>drewniany</base><ctag>adj:pl:voc:m2:pos</ctag></lex>
    <lex><base>drewniany</base><ctag>adj:pl:nom:m3:pos</ctag></lex>
    <lex><base>drewniany</base><ctag>adj:pl:acc:m3:pos</ctag></lex>
    <lex><base>drewniany</base><ctag>adj:pl:voc:m3:pos</ctag></lex>
    <lex><base>drewniany</base><ctag>adj:pl:nom:f:pos</ctag></lex>
    <lex><base>drewniany</base><ctag>adj:pl:acc:f:pos</ctag></lex>
    <lex><base>drewniany</base><ctag>adj:pl:voc:f:pos</ctag></lex>
    <lex disamb="1"><base>drewniany</base><ctag>adj:pl:nom:n:pos</ctag></lex>
    <lex><base>drewniany</base><ctag>adj:pl:acc:n:pos</ctag></lex>
    <lex><base>drewniany</base><ctag>adj:pl:voc:n:pos</ctag></lex>
   </tok>
   <tok>
    <orth>umocnienia</orth>
    <lex><base>umocnienie</base><ctag>subst:sg:gen:n</ctag></lex>
    <lex disamb="1"><base>umocnienie</base><ctag>subst:pl:nom:n</ctag></lex>
    <lex><base>umocnienie</base><ctag>subst:pl:acc:n</ctag></lex>
    <lex><base>umocnienie</base><ctag>subst:pl:voc:n</ctag></lex>
    <lex><base>umocnić</base><ctag>ger:sg:gen:n:perf:aff</ctag></lex>
   </tok>
   <tok>
    <orth>załoga</orth>
    <lex disamb="1"><base>załoga</base><ctag>subst:sg:nom:f</ctag></lex>
   </tok>
   <tok>
    <orth>wraz</orth>
    <lex disamb="1"><base>wraz</base><ctag>burk</ctag></lex>
    <lex><base>wraz</base><ctag>subst:sg:nom:m3</ctag></lex>
    <lex><base>wraz</base><ctag>subst:sg:acc:m3</ctag></lex>
   </tok>
   <tok>
    <orth>z</orth>
    <lex><base>z</base><ctag>prep:gen:nwok</ctag></lex>
    <lex><base>z</base><ctag>prep:acc:nwok</ctag></lex>
    <lex disamb="1"><base>z</base><ctag>prep:inst:nwok</ctag></lex>
    <lex><base>z</base><ctag>qub</ctag></lex>
    <lex><base>zeszyt</base><ctag>brev:pun</ctag></lex>
   </tok>
   <tok>
    <orth>chroniącymi</orth>
    <lex disamb="1"><base>chronić</base><ctag>pact:pl:inst:m1:imperf:aff</ctag></lex>
    <lex><base>chronić</base><ctag>pact:pl:inst:m2:imperf:aff</ctag></lex>
    <lex><base>chronić</base><ctag>pact:pl:inst:m3:imperf:aff</ctag></lex>
    <lex><base>chronić</base><ctag>pact:pl:inst:f:imperf:aff</ctag></lex>
    <lex><base>chronić</base><ctag>pact:pl:inst:n:imperf:aff</ctag></lex>
   </tok>
   <tok>
    <orth>się</orth>
    <lex disamb="1"><base>się</base><ctag>qub</ctag></lex>
   </tok>
   <tok>
    <orth>w</orth>
    <lex><base>w</base><ctag>prep:acc:nwok</ctag></lex>
    <lex disamb="1"><base>w</base><ctag>prep:loc:nwok</ctag></lex>
    <lex><base>wiek</base><ctag>brev:pun</ctag></lex>
    <lex><base>wielki</base><ctag>brev:pun</ctag></lex>
    <lex><base>wiersz</base><ctag>brev:pun</ctag></lex>
    <lex><base>wieś</base><ctag>brev:pun</ctag></lex>
    <lex><base>wyspa</base><ctag>brev:pun</ctag></lex>
   </tok>
   <tok>
    <orth>grodzie</orth>
    <lex><base>grodź</base><ctag>subst:pl:nom:f</ctag></lex>
    <lex><base>grodź</base><ctag>subst:pl:acc:f</ctag></lex>
    <lex><base>grodź</base><ctag>subst:pl:voc:f</ctag></lex>
    <lex disamb="1"><base>gród</base><ctag>subst:sg:loc:m3</ctag></lex>
    <lex><base>gród</base><ctag>subst:sg:voc:m3</ctag></lex>
    <lex><base>gródź</base><ctag>subst:pl:nom:f</ctag></lex>
    <lex><base>gródź</base><ctag>subst:pl:acc:f</ctag></lex>
    <lex><base>gródź</base><ctag>subst:pl:voc:f</ctag></lex>
   </tok>
   <tok>
    <orth>mieszczanami</orth>
    <lex disamb="1"><base>mieszczan</base><ctag>subst:pl:inst:m1</ctag></lex>
    <lex disamb="1"><base>mieszczanin</base><ctag>subst:pl:inst:m1</ctag></lex>
   </tok>
   <tok>
    <orth>wytrzymała</orth>
    <lex disamb="1"><base>wytrzymać</base><ctag>praet:sg:f:perf</ctag></lex>
    <lex><base>wytrzymały</base><ctag>adj:sg:nom:f:pos</ctag></lex>
    <lex><base>wytrzymały</base><ctag>adj:sg:voc:f:pos</ctag></lex>
   </tok>
   <tok>
    <orth>oblężenie</orth>
    <lex><base>oblężenie</base><ctag>subst:sg:nom:n</ctag></lex>
    <lex disamb="1"><base>oblężenie</base><ctag>subst:sg:acc:n</ctag></lex>
    <lex><base>oblężenie</base><ctag>subst:sg:voc:n</ctag></lex>
    <lex><base>oblężeć</base><ctag>ger:sg:nom:n:perf:aff</ctag></lex>
    <lex><base>oblężeć</base><ctag>ger:sg:acc:n:perf:aff</ctag></lex>
   </tok>
   <ns/>
   <tok>
    <orth>,</orth>
    <lex disamb="1"><base>,</base><ctag>interp</ctag></lex>
   </tok>
   <tok>
    <orth>które</orth>
    <lex disamb="1"><base>który</base><ctag>adj:sg:nom:n:pos</ctag></lex>
    <lex><base>który</base><ctag>adj:sg:acc:n:pos</ctag></lex>
    <lex><base>który</base><ctag>adj:sg:voc:n:pos</ctag></lex>
    <lex><base>który</base><ctag>adj:pl:nom:m2:pos</ctag></lex>
    <lex><base>który</base><ctag>adj:pl:acc:m2:pos</ctag></lex>
    <lex><base>który</base><ctag>adj:pl:voc:m2:pos</ctag></lex>
    <lex><base>który</base><ctag>adj:pl:nom:m3:pos</ctag></lex>
    <lex><base>który</base><ctag>adj:pl:acc:m3:pos</ctag></lex>
    <lex><base>który</base><ctag>adj:pl:voc:m3:pos</ctag></lex>
    <lex><base>który</base><ctag>adj:pl:nom:f:pos</ctag></lex>
    <lex><base>który</base><ctag>adj:pl:acc:f:pos</ctag></lex>
    <lex><base>który</base><ctag>adj:pl:voc:f:pos</ctag></lex>
    <lex><base>który</base><ctag>adj:pl:nom:n:pos</ctag></lex>
    <lex><base>który</base><ctag>adj:pl:acc:n:pos</ctag></lex>
    <lex><base>który</base><ctag>adj:pl:voc:n:pos</ctag></lex>
   </tok>
   <tok>
    <orth>trwało</orth>
    <lex disamb="1"><base>trwać</base><ctag>praet:sg:n:imperf</ctag></lex>
    <lex><base>trwało</base><ctag>adv:pos</ctag></lex>
   </tok>
   <tok>
    <orth>od</orth>
    <lex><base>Oda</base><ctag>subst:pl:gen:f</ctag></lex>
    <lex disamb="1"><base>od</base><ctag>prep:gen:nwok</ctag></lex>
   </tok>
   <tok>
    <orth>8</orth>
    <lex><base>8</base><ctag>ign</ctag></lex>
    <lex disamb="1"><base>8</base><ctag>num:pl:gen:m3:congr</ctag></lex>
   </tok>
   <tok>
    <orth>do</orth>
    <lex disamb="1"><base>do</base><ctag>prep:gen</ctag></lex>
    <lex><base>do</base><ctag>subst:sg:nom:n</ctag></lex>
    <lex><base>do</base><ctag>subst:sg:gen:n</ctag></lex>
    <lex><base>do</base><ctag>subst:sg:dat:n</ctag></lex>
    <lex><base>do</base><ctag>subst:sg:acc:n</ctag></lex>
    <lex><base>do</base><ctag>subst:sg:inst:n</ctag></lex>
    <lex><base>do</base><ctag>subst:sg:loc:n</ctag></lex>
    <lex><base>do</base><ctag>subst:sg:voc:n</ctag></lex>
    <lex><base>do</base><ctag>subst:pl:nom:n</ctag></lex>
    <lex><base>do</base><ctag>subst:pl:gen:n</ctag></lex>
    <lex><base>do</base><ctag>subst:pl:dat:n</ctag></lex>
    <lex><base>do</base><ctag>subst:pl:acc:n</ctag></lex>
    <lex><base>do</base><ctag>subst:pl:inst:n</ctag></lex>
    <lex><base>do</base><ctag>subst:pl:loc:n</ctag></lex>
    <lex><base>do</base><ctag>subst:pl:voc:n</ctag></lex>
   </tok>
   <tok>
    <orth>12</orth>
    <lex><base>12</base><ctag>ign</ctag></lex>
    <lex disamb="1"><base>12</base><ctag>num:pl:gen:m3:congr</ctag></lex>
   </tok>
   <tok>
    <orth>dni</orth>
    <lex><base>dzień</base><ctag>subst:pl:nom:m3</ctag></lex>
    <lex disamb="1"><base>dzień</base><ctag>subst:pl:gen:m3</ctag></lex>
    <lex><base>dzień</base><ctag>subst:pl:acc:m3</ctag></lex>
    <lex><base>dzień</base><ctag>subst:pl:voc:m3</ctag></lex>
   </tok>
   <ns/>
   <tok>
    <orth>.</orth>
    <lex disamb="1"><base>.</base><ctag>interp</ctag></lex>
   </tok>
  </sentence>
  <sentence id="sent9">
   <tok>
    <orth>Co</orth>
    <lex><base>CO</base><ctag>subst:sg:nom:n</ctag></lex>
    <lex><base>CO</base><ctag>subst:sg:gen:n</ctag></lex>
    <lex><base>CO</base><ctag>subst:sg:dat:n</ctag></lex>
    <lex><base>CO</base><ctag>subst:sg:acc:n</ctag></lex>
    <lex><base>CO</base><ctag>subst:sg:inst:n</ctag></lex>
    <lex><base>CO</base><ctag>subst:sg:loc:n</ctag></lex>
    <lex><base>CO</base><ctag>subst:sg:voc:n</ctag></lex>
    <lex><base>CO</base><ctag>subst:pl:nom:n</ctag></lex>
    <lex><base>CO</base><ctag>subst:pl:gen:n</ctag></lex>
    <lex><base>CO</base><ctag>subst:pl:dat:n</ctag></lex>
    <lex><base>CO</base><ctag>subst:pl:acc:n</ctag></lex>
    <lex><base>CO</base><ctag>subst:pl:inst:n</ctag></lex>
    <lex><base>CO</base><ctag>subst:pl:loc:n</ctag></lex>
    <lex><base>CO</base><ctag>subst:pl:voc:n</ctag></lex>
    <lex disamb="1"><base>co</base><ctag>comp</ctag></lex>
    <lex><base>co</base><ctag>prep:nom</ctag></lex>
    <lex><base>co</base><ctag>prep:acc</ctag></lex>
    <lex><base>co</base><ctag>qub</ctag></lex>
    <lex><base>co</base><ctag>subst:sg:nom:n</ctag></lex>
    <lex><base>co</base><ctag>subst:sg:gen:n</ctag></lex>
    <lex><base>co</base><ctag>subst:sg:acc:n</ctag></lex>
    <ann chan="nam">0</ann>
   </tok>
   <tok>
    <orth>do</orth>
    <lex disamb="1"><base>do</base><ctag>prep:gen</ctag></lex>
    <lex><base>do</base><ctag>subst:sg:nom:n</ctag></lex>
    <lex><base>do</base><ctag>subst:sg:gen:n</ctag></lex>
    <lex><base>do</base><ctag>subst:sg:dat:n</ctag></lex>
    <lex><base>do</base><ctag>subst:sg:acc:n</ctag></lex>
    <lex><base>do</base><ctag>subst:sg:inst:n</ctag></lex>
    <lex><base>do</base><ctag>subst:sg:loc:n</ctag></lex>
    <lex><base>do</base><ctag>subst:sg:voc:n</ctag></lex>
    <lex><base>do</base><ctag>subst:pl:nom:n</ctag></lex>
    <lex><base>do</base><ctag>subst:pl:gen:n</ctag></lex>
    <lex><base>do</base><ctag>subst:pl:dat:n</ctag></lex>
    <lex><base>do</base><ctag>subst:pl:acc:n</ctag></lex>
    <lex><base>do</base><ctag>subst:pl:inst:n</ctag></lex>
    <lex><base>do</base><ctag>subst:pl:loc:n</ctag></lex>
    <lex><base>do</base><ctag>subst:pl:voc:n</ctag></lex>
    <ann chan="nam">0</ann>
   </tok>
   <tok>
    <orth>przyczyny</orth>
    <lex disamb="1"><base>przyczyna</base><ctag>subst:sg:gen:f</ctag></lex>
    <lex><base>przyczyna</base><ctag>subst:pl:nom:f</ctag></lex>
    <lex><base>przyczyna</base><ctag>subst:pl:acc:f</ctag></lex>
    <lex><base>przyczyna</base><ctag>subst:pl:voc:f</ctag></lex>
    <ann chan="nam">0</ann>
   </tok>
   <tok>
    <orth>odstąpienia</orth>
    <lex disamb="1"><base>odstąpić</base><ctag>ger:sg:gen:n:perf:aff</ctag></lex>
    <ann chan="nam">0</ann>
   </tok>
   <tok>
    <orth>Tatarów</orth>
    <lex disamb="1"><base>Tatar</base><ctag>subst:pl:gen:m1</ctag></lex>
    <lex><base>Tatar</base><ctag>subst:pl:acc:m1</ctag></lex>
    <lex><base>tatar</base><ctag>subst:pl:gen:m2</ctag></lex>
    <lex><base>tatar</base><ctag>subst:pl:gen:m3</ctag></lex>
    <ann chan="nam">1</ann>
   </tok>
   <tok>
    <orth>od</orth>
    <lex><base>Oda</base><ctag>subst:pl:gen:f</ctag></lex>
    <lex disamb="1"><base>od</base><ctag>prep:gen:nwok</ctag></lex>
    <ann chan="nam">0</ann>
   </tok>
   <tok>
    <orth>Lublina</orth>
    <lex disamb="1"><base>Lublin</base><ctag>subst:sg:gen:m3</ctag></lex>
    <lex disamb="1"><base>lublin</base><ctag>subst:sg:gen:m3</ctag></lex>
    <ann chan="nam">2</ann>
   </tok>
   <tok>
    <orth>istnieją</orth>
    <lex disamb="1"><base>istnieć</base><ctag>fin:pl:ter:imperf</ctag></lex>
    <ann chan="nam">0</ann>
   </tok>
   <tok>
    <orth>dwie</orth>
    <lex disamb="1"><base>dwa</base><ctag>num:pl:nom:f:congr</ctag></lex>
    <lex><base>dwa</base><ctag>num:pl:acc:f:congr</ctag></lex>
    <lex><base>dwa</base><ctag>num:pl:voc:f:congr</ctag></lex>
    <ann chan="nam">0</ann>
   </tok>
   <tok>
    <orth>sprzeczne</orth>
    <lex><base>sprzeczny</base><ctag>adj:sg:nom:n:pos</ctag></lex>
    <lex><base>sprzeczny</base><ctag>adj:sg:acc:n:pos</ctag></lex>
    <lex><base>sprzeczny</base><ctag>adj:sg:voc:n:pos</ctag></lex>
    <lex><base>sprzeczny</base><ctag>adj:pl:nom:m2:pos</ctag></lex>
    <lex><base>sprzeczny</base><ctag>adj:pl:acc:m2:pos</ctag></lex>
    <lex><base>sprzeczny</base><ctag>adj:pl:voc:m2:pos</ctag></lex>
    <lex><base>sprzeczny</base><ctag>adj:pl:nom:m3:pos</ctag></lex>
    <lex><base>sprzeczny</base><ctag>adj:pl:acc:m3:pos</ctag></lex>
    <lex><base>sprzeczny</base><ctag>adj:pl:voc:m3:pos</ctag></lex>
    <lex disamb="1"><base>sprzeczny</base><ctag>adj:pl:nom:f:pos</ctag></lex>
    <lex><base>sprzeczny</base><ctag>adj:pl:acc:f:pos</ctag></lex>
    <lex><base>sprzeczny</base><ctag>adj:pl:voc:f:pos</ctag></lex>
    <lex><base>sprzeczny</base><ctag>adj:pl:nom:n:pos</ctag></lex>
    <lex><base>sprzeczny</base><ctag>adj:pl:acc:n:pos</ctag></lex>
    <lex><base>sprzeczny</base><ctag>adj:pl:voc:n:pos</ctag></lex>
    <ann chan="nam">0</ann>
   </tok>
   <tok>
    <orth>hipotezy</orth>
    <lex><base>hipoteza</base><ctag>subst:sg:gen:f</ctag></lex>
    <lex disamb="1"><base>hipoteza</base><ctag>subst:pl:nom:f</ctag></lex>
    <lex><base>hipoteza</base><ctag>subst:pl:acc:f</ctag></lex>
    <lex><base>hipoteza</base><ctag>subst:pl:voc:f</ctag></lex>
    <ann chan="nam">0</ann>
   </tok>
   <ns/>
   <tok>
    <orth>.</orth>
    <lex disamb="1"><base>.</base><ctag>interp</ctag></lex>
    <ann chan="nam">0</ann>
   </tok>
  </sentence>
 </chunk>
 <chunk id="ch5">
  <sentence id="sent10">
   <tok>
    <orth>Według</orth>
    <lex disamb="1"><base>według</base><ctag>prep:gen</ctag></lex>
    <ann chan="nam">0</ann>
   </tok>
   <tok>
    <orth>pierwszej</orth>
    <lex><base>pierwsza</base><ctag>subst:sg:gen:f</ctag></lex>
    <lex><base>pierwsza</base><ctag>subst:sg:dat:f</ctag></lex>
    <lex><base>pierwsza</base><ctag>subst:sg:loc:f</ctag></lex>
    <lex disamb="1"><base>pierwszy</base><ctag>adj:sg:gen:f:pos</ctag></lex>
    <lex><base>pierwszy</base><ctag>adj:sg:dat:f:pos</ctag></lex>
    <lex><base>pierwszy</base><ctag>adj:sg:loc:f:pos</ctag></lex>
    <ann chan="nam">0</ann>
   </tok>
   <tok>
    <orth>Kazimierz</orth>
    <lex disamb="1"><base>Kazimierz</base><ctag>subst:sg:nom:m1</ctag></lex>
    <lex><base>Kazimierz</base><ctag>subst:sg:nom:m3</ctag></lex>
    <lex><base>Kazimierz</base><ctag>subst:sg:acc:m3</ctag></lex>
    <ann chan="nam">1</ann>
   </tok>
   <tok>
    <orth>Wielki</orth>
    <lex disamb="1"><base>wielki</base><ctag>adj:sg:nom:m1:pos</ctag></lex>
    <lex><base>wielki</base><ctag>adj:sg:voc:m1:pos</ctag></lex>
    <lex><base>wielki</base><ctag>adj:sg:nom:m2:pos</ctag></lex>
    <lex><base>wielki</base><ctag>adj:sg:voc:m2:pos</ctag></lex>
    <lex><base>wielki</base><ctag>adj:sg:nom:m3:pos</ctag></lex>
    <lex><base>wielki</base><ctag>adj:sg:acc:m3:pos</ctag></lex>
    <lex><base>wielki</base><ctag>adj:sg:voc:m3:pos</ctag></lex>
    <lex><base>wielki</base><ctag>subst:sg:nom:m1</ctag></lex>
    <lex><base>wielki</base><ctag>subst:sg:voc:m1</ctag></lex>
    <ann chan="nam">1</ann>
   </tok>
   <tok>
    <orth>stoczył</orth>
    <lex disamb="1"><base>stoczyć</base><ctag>praet:sg:m1:perf</ctag></lex>
    <lex><base>stoczyć</base><ctag>praet:sg:m2:perf</ctag></lex>
    <lex><base>stoczyć</base><ctag>praet:sg:m3:perf</ctag></lex>
    <ann chan="nam">0</ann>
   </tok>
   <tok>
    <orth>bitwę</orth>
    <lex disamb="1"><base>bitwa</base><ctag>subst:sg:acc:f</ctag></lex>
    <ann chan="nam">0</ann>
   </tok>
   <tok>
    <orth>z</orth>
    <lex><base>z</base><ctag>prep:gen:nwok</ctag></lex>
    <lex><base>z</base><ctag>prep:acc:nwok</ctag></lex>
    <lex disamb="1"><base>z</base><ctag>prep:inst:nwok</ctag></lex>
    <lex><base>z</base><ctag>qub</ctag></lex>
    <lex><base>zeszyt</base><ctag>brev:pun</ctag></lex>
    <ann chan="nam">0</ann>
   </tok>
   <tok>
    <orth>Tatarami</orth>
    <lex disamb="1"><base>Tatar</base><ctag>subst:pl:inst:m1</ctag></lex>
    <lex><base>tatar</base><ctag>subst:pl:inst:m2</ctag></lex>
    <lex><base>tatar</base><ctag>subst:pl:inst:m3</ctag></lex>
    <ann chan="nam">2</ann>
   </tok>
   <tok>
    <orth>we</orth>
    <lex><base>w</base><ctag>prep:acc:wok</ctag></lex>
    <lex disamb="1"><base>w</base><ctag>prep:loc:wok</ctag></lex>
    <lex><base>we</base><ctag>subst:sg:nom:n</ctag></lex>
    <lex><base>we</base><ctag>subst:sg:gen:n</ctag></lex>
    <lex><base>we</base><ctag>subst:sg:dat:n</ctag></lex>
    <lex><base>we</base><ctag>subst:sg:acc:n</ctag></lex>
    <lex><base>we</base><ctag>subst:sg:inst:n</ctag></lex>
    <lex><base>we</base><ctag>subst:sg:loc:n</ctag></lex>
    <lex><base>we</base><ctag>subst:sg:voc:n</ctag></lex>
    <lex><base>we</base><ctag>subst:pl:nom:n</ctag></lex>
    <lex><base>we</base><ctag>subst:pl:gen:n</ctag></lex>
    <lex><base>we</base><ctag>subst:pl:dat:n</ctag></lex>
    <lex><base>we</base><ctag>subst:pl:acc:n</ctag></lex>
    <lex><base>we</base><ctag>subst:pl:inst:n</ctag></lex>
    <lex><base>we</base><ctag>subst:pl:loc:n</ctag></lex>
    <lex><base>we</base><ctag>subst:pl:voc:n</ctag></lex>
    <ann chan="nam">0</ann>
   </tok>
   <tok>
    <orth>wsi</orth>
    <lex><base>WSI</base><ctag>subst:sg:nom:n</ctag></lex>
    <lex><base>WSI</base><ctag>subst:sg:gen:n</ctag></lex>
    <lex><base>WSI</base><ctag>subst:sg:dat:n</ctag></lex>
    <lex><base>WSI</base><ctag>subst:sg:acc:n</ctag></lex>
    <lex><base>WSI</base><ctag>subst:sg:inst:n</ctag></lex>
    <lex><base>WSI</base><ctag>subst:sg:loc:n</ctag></lex>
    <lex><base>WSI</base><ctag>subst:sg:voc:n</ctag></lex>
    <lex><base>WSI</base><ctag>subst:pl:nom:n</ctag></lex>
    <lex><base>WSI</base><ctag>subst:pl:gen:n</ctag></lex>
    <lex><base>WSI</base><ctag>subst:pl:dat:n</ctag></lex>
    <lex><base>WSI</base><ctag>subst:pl:acc:n</ctag></lex>
    <lex><base>WSI</base><ctag>subst:pl:inst:n</ctag></lex>
    <lex><base>WSI</base><ctag>subst:pl:loc:n</ctag></lex>
    <lex><base>WSI</base><ctag>subst:pl:voc:n</ctag></lex>
    <lex><base>wieś</base><ctag>subst:sg:gen:f</ctag></lex>
    <lex><base>wieś</base><ctag>subst:sg:dat:f</ctag></lex>
    <lex disamb="1"><base>wieś</base><ctag>subst:sg:loc:f</ctag></lex>
    <lex><base>wieś</base><ctag>subst:sg:voc:f</ctag></lex>
    <lex><base>wieś</base><ctag>subst:pl:nom:f</ctag></lex>
    <lex><base>wieś</base><ctag>subst:pl:gen:f</ctag></lex>
    <lex><base>wieś</base><ctag>subst:pl:acc:f</ctag></lex>
    <lex><base>wieś</base><ctag>subst:pl:voc:f</ctag></lex>
    <ann chan="nam">0</ann>
   </tok>
   <tok>
    <orth>nieopodal</orth>
    <lex><base>nieopodal</base><ctag>adv</ctag></lex>
    <lex disamb="1"><base>nieopodal</base><ctag>prep:gen</ctag></lex>
    <ann chan="nam">0</ann>
   </tok>
   <tok>
    <orth>Lublina</orth>
    <lex disamb="1"><base>Lublin</base><ctag>subst:sg:gen:m3</ctag></lex>
    <lex disamb="1"><base>lublin</base><ctag>subst:sg:gen:m3</ctag></lex>
    <ann chan="nam">3</ann>
   </tok>
   <tok>
    <orth>na</orth>
    <lex><base>na</base><ctag>interj</ctag></lex>
    <lex><base>na</base><ctag>prep:acc</ctag></lex>
    <lex disamb="1"><base>na</base><ctag>prep:loc</ctag></lex>
    <ann chan="nam">0</ann>
   </tok>
   <tok>
    <orth>prawym</orth>
    <lex><base>prawa</base><ctag>subst:pl:dat:f</ctag></lex>
    <lex><base>prawy</base><ctag>adj:sg:inst:m1:pos</ctag></lex>
    <lex><base>prawy</base><ctag>adj:sg:loc:m1:pos</ctag></lex>
    <lex><base>prawy</base><ctag>adj:sg:inst:m2:pos</ctag></lex>
    <lex><base>prawy</base><ctag>adj:sg:loc:m2:pos</ctag></lex>
    <lex><base>prawy</base><ctag>adj:sg:inst:m3:pos</ctag></lex>
    <lex disamb="1"><base>prawy</base><ctag>adj:sg:loc:m3:pos</ctag></lex>
    <lex><base>prawy</base><ctag>adj:sg:inst:n:pos</ctag></lex>
    <lex><base>prawy</base><ctag>adj:sg:loc:n:pos</ctag></lex>
    <lex><base>prawy</base><ctag>adj:pl:dat:m1:pos</ctag></lex>
    <lex><base>prawy</base><ctag>adj:pl:dat:m2:pos</ctag></lex>
    <lex><base>prawy</base><ctag>adj:pl:dat:m3:pos</ctag></lex>
    <lex><base>prawy</base><ctag>adj:pl:dat:f:pos</ctag></lex>
    <lex><base>prawy</base><ctag>adj:pl:dat:n:pos</ctag></lex>
    <lex><base>prawy</base><ctag>subst:sg:inst:m3</ctag></lex>
    <lex><base>prawy</base><ctag>subst:sg:loc:m3</ctag></lex>
    <lex><base>prawy</base><ctag>subst:pl:dat:m3</ctag></lex>
    <ann chan="nam">0</ann>
   </tok>
   <tok>
    <orth>brzegu</orth>
    <lex><base>brzeg</base><ctag>subst:sg:gen:m3</ctag></lex>
    <lex disamb="1"><base>brzeg</base><ctag>subst:sg:loc:m3</ctag></lex>
    <lex><base>brzeg</base><ctag>subst:sg:voc:m3</ctag></lex>
    <ann chan="nam">0</ann>
   </tok>
   <tok>
    <orth>Bystrzycy</orth>
    <lex disamb="1"><base>Bystrzyca</base><ctag>subst:sg:gen:f</ctag></lex>
    <lex><base>Bystrzyca</base><ctag>subst:sg:dat:f</ctag></lex>
    <lex><base>Bystrzyca</base><ctag>subst:sg:loc:f</ctag></lex>
    <lex disamb="1"><base>bystrzyca</base><ctag>subst:sg:gen:f</ctag></lex>
    <lex><base>bystrzyca</base><ctag>subst:sg:dat:f</ctag></lex>
    <lex><base>bystrzyca</base><ctag>subst:sg:loc:f</ctag></lex>
    <ann chan="nam">4</ann>
   </tok>
   <ns/>
   <tok>
    <orth>,</orth>
    <lex disamb="1"><base>,</base><ctag>interp</ctag></lex>
    <ann chan="nam">0</ann>
   </tok>
   <tok>
    <orth>rozbijając</orth>
    <lex disamb="1"><base>rozbijać</base><ctag>pcon:imperf</ctag></lex>
    <ann chan="nam">0</ann>
   </tok>
   <tok>
    <orth>ich</orth>
    <lex><base>on</base><ctag>ppron3:pl:gen:m1:ter:akc:npraep</ctag></lex>
    <lex><base>on</base><ctag>ppron3:pl:gen:m1:ter:nakc:npraep</ctag></lex>
    <lex disamb="1"><base>on</base><ctag>ppron3:pl:acc:m1:ter:akc:npraep</ctag></lex>
    <lex><base>on</base><ctag>ppron3:pl:acc:m1:ter:nakc:npraep</ctag></lex>
    <lex><base>on</base><ctag>ppron3:pl:gen:m2:ter:akc:npraep</ctag></lex>
    <lex><base>on</base><ctag>ppron3:pl:gen:m2:ter:nakc:npraep</ctag></lex>
    <lex><base>on</base><ctag>ppron3:pl:gen:m3:ter:akc:npraep</ctag></lex>
    <lex><base>on</base><ctag>ppron3:pl:gen:m3:ter:nakc:npraep</ctag></lex>
    <lex><base>on</base><ctag>ppron3:pl:gen:f:ter:akc:npraep</ctag></lex>
    <lex><base>on</base><ctag>ppron3:pl:gen:f:ter:nakc:npraep</ctag></lex>
    <lex><base>on</base><ctag>ppron3:pl:gen:n:ter:akc:npraep</ctag></lex>
    <lex><base>on</base><ctag>ppron3:pl:gen:n:ter:nakc:npraep</ctag></lex>
    <ann chan="nam">0</ann>
   </tok>
   <tok>
    <orth>główne</orth>
    <lex><base>główny</base><ctag>adj:sg:nom:n:pos</ctag></lex>
    <lex><base>główny</base><ctag>adj:sg:acc:n:pos</ctag></lex>
    <lex><base>główny</base><ctag>adj:sg:voc:n:pos</ctag></lex>
    <lex><base>główny</base><ctag>adj:pl:nom:m2:pos</ctag></lex>
    <lex><base>główny</base><ctag>adj:pl:acc:m2:pos</ctag></lex>
    <lex><base>główny</base><ctag>adj:pl:voc:m2:pos</ctag></lex>
    <lex><base>główny</base><ctag>adj:pl:nom:m3:pos</ctag></lex>
    <lex><base>główny</base><ctag>adj:pl:acc:m3:pos</ctag></lex>
    <lex><base>główny</base><ctag>adj:pl:voc:m3:pos</ctag></lex>
    <lex><base>główny</base><ctag>adj:pl:nom:f:pos</ctag></lex>
    <lex disamb="1"><base>główny</base><ctag>adj:pl:acc:f:pos</ctag></lex>
    <lex><base>główny</base><ctag>adj:pl:voc:f:pos</ctag></lex>
    <lex><base>główny</base><ctag>adj:pl:nom:n:pos</ctag></lex>
    <lex><base>główny</base><ctag>adj:pl:acc:n:pos</ctag></lex>
    <lex><base>główny</base><ctag>adj:pl:voc:n:pos</ctag></lex>
    <ann chan="nam">0</ann>
   </tok>
   <tok>
    <orth>siły</orth>
    <lex><base>siła</base><ctag>subst:sg:gen:f</ctag></lex>
    <lex><base>siła</base><ctag>subst:pl:nom:f</ctag></lex>
    <lex disamb="1"><base>siła</base><ctag>subst:pl:acc:f</ctag></lex>
    <lex><base>siła</base><ctag>subst:pl:voc:f</ctag></lex>
    <lex><base>siły</base><ctag>subst:pl:nom:n</ctag></lex>
    <lex><base>siły</base><ctag>subst:pl:acc:n</ctag></lex>
    <lex><base>siły</base><ctag>subst:pl:voc:n</ctag></lex>
    <ann chan="nam">0</ann>
   </tok>
   <ns/>
   <tok>
    <orth>.</orth>
    <lex disamb="1"><base>.</base><ctag>interp</ctag></lex>
    <ann chan="nam">0</ann>
   </tok>
  </sentence>
  <sentence id="sent11">
   <tok>
    <orth>Od</orth>
    <lex><base>Oda</base><ctag>subst:pl:gen:f</ctag></lex>
    <lex disamb="1"><base>od</base><ctag>prep:gen:nwok</ctag></lex>
    <ann chan="nam">0</ann>
   </tok>
   <tok>
    <orth>legendarnej</orth>
    <lex disamb="1"><base>legendarny</base><ctag>adj:sg:gen:f:pos</ctag></lex>
    <lex><base>legendarny</base><ctag>adj:sg:dat:f:pos</ctag></lex>
    <lex><base>legendarny</base><ctag>adj:sg:loc:f:pos</ctag></lex>
    <ann chan="nam">0</ann>
   </tok>
   <tok>
    <orth>bitwy</orth>
    <lex disamb="1"><base>bitwa</base><ctag>subst:sg:gen:f</ctag></lex>
    <lex><base>bitwa</base><ctag>subst:pl:nom:f</ctag></lex>
    <lex><base>bitwa</base><ctag>subst:pl:acc:f</ctag></lex>
    <lex><base>bitwa</base><ctag>subst:pl:voc:f</ctag></lex>
    <ann chan="nam">0</ann>
   </tok>
   <tok>
    <orth>miała</orth>
    <lex disamb="1"><base>mieć</base><ctag>praet:sg:f:imperf</ctag></lex>
    <ann chan="nam">0</ann>
   </tok>
   <tok>
    <orth>się</orth>
    <lex disamb="1"><base>się</base><ctag>qub</ctag></lex>
    <ann chan="nam">0</ann>
   </tok>
   <tok>
    <orth>wziąć</orth>
    <lex disamb="1"><base>wziąć</base><ctag>inf:perf</ctag></lex>
    <ann chan="nam">0</ann>
   </tok>
   <tok>
    <orth>późniejsza</orth>
    <lex disamb="1"><base>późny</base><ctag>adj:sg:nom:f:com</ctag></lex>
    <lex><base>późny</base><ctag>adj:sg:voc:f:com</ctag></lex>
    <ann chan="nam">0</ann>
   </tok>
   <tok>
    <orth>nazwa</orth>
    <lex disamb="1"><base>nazwa</base><ctag>subst:sg:nom:f</ctag></lex>
    <ann chan="nam">0</ann>
   </tok>
   <tok>
    <orth>wsi</orth>
    <lex><base>WSI</base><ctag>subst:sg:nom:n</ctag></lex>
    <lex><base>WSI</base><ctag>subst:sg:gen:n</ctag></lex>
    <lex><base>WSI</base><ctag>subst:sg:dat:n</ctag></lex>
    <lex><base>WSI</base><ctag>subst:sg:acc:n</ctag></lex>
    <lex><base>WSI</base><ctag>subst:sg:inst:n</ctag></lex>
    <lex><base>WSI</base><ctag>subst:sg:loc:n</ctag></lex>
    <lex><base>WSI</base><ctag>subst:sg:voc:n</ctag></lex>
    <lex><base>WSI</base><ctag>subst:pl:nom:n</ctag></lex>
    <lex><base>WSI</base><ctag>subst:pl:gen:n</ctag></lex>
    <lex><base>WSI</base><ctag>subst:pl:dat:n</ctag></lex>
    <lex><base>WSI</base><ctag>subst:pl:acc:n</ctag></lex>
    <lex><base>WSI</base><ctag>subst:pl:inst:n</ctag></lex>
    <lex><base>WSI</base><ctag>subst:pl:loc:n</ctag></lex>
    <lex><base>WSI</base><ctag>subst:pl:voc:n</ctag></lex>
    <lex disamb="1"><base>wieś</base><ctag>subst:sg:gen:f</ctag></lex>
    <lex><base>wieś</base><ctag>subst:sg:dat:f</ctag></lex>
    <lex><base>wieś</base><ctag>subst:sg:loc:f</ctag></lex>
    <lex><base>wieś</base><ctag>subst:sg:voc:f</ctag></lex>
    <lex><base>wieś</base><ctag>subst:pl:nom:f</ctag></lex>
    <lex><base>wieś</base><ctag>subst:pl:gen:f</ctag></lex>
    <lex><base>wieś</base><ctag>subst:pl:acc:f</ctag></lex>
    <lex><base>wieś</base><ctag>subst:pl:voc:f</ctag></lex>
    <ann chan="nam">0</ann>
   </tok>
   <ns/>
   <tok>
    <orth>,</orth>
    <lex disamb="1"><base>,</base><ctag>interp</ctag></lex>
    <ann chan="nam">0</ann>
   </tok>
   <tok>
    <orth>a</orth>
    <lex disamb="1"><base>a</base><ctag>conj</ctag></lex>
    <lex><base>a</base><ctag>interj</ctag></lex>
    <lex><base>a</base><ctag>prep:nom</ctag></lex>
    <lex><base>a</base><ctag>qub</ctag></lex>
    <lex><base>albo</base><ctag>brev:pun</ctag></lex>
    <ann chan="nam">0</ann>
   </tok>
   <tok>
    <orth>następnie</orth>
    <lex disamb="1"><base>następnie</base><ctag>adv</ctag></lex>
    <ann chan="nam">0</ann>
   </tok>
   <tok>
    <orth>dzielnicy</orth>
    <lex disamb="1"><base>dzielnica</base><ctag>subst:sg:gen:f</ctag></lex>
    <lex><base>dzielnica</base><ctag>subst:sg:dat:f</ctag></lex>
    <lex><base>dzielnica</base><ctag>subst:sg:loc:f</ctag></lex>
    <ann chan="nam">0</ann>
   </tok>
   <tok>
    <orth>Lublina</orth>
    <lex disamb="1"><base>Lublin</base><ctag>subst:sg:gen:m3</ctag></lex>
    <lex disamb="1"><base>lublin</base><ctag>subst:sg:gen:m3</ctag></lex>
    <ann chan="nam">1</ann>
   </tok>
   <ns/>
   <tok>
    <orth>,</orth>
    <lex disamb="1"><base>,</base><ctag>interp</ctag></lex>
    <ann chan="nam">0</ann>
   </tok>
   <tok>
    <orth>Tatary</orth>
    <lex><base>Tatar</base><ctag>depr:pl:nom:m2</ctag></lex>
    <lex><base>Tatar</base><ctag>depr:pl:voc:m2</ctag></lex>
    <lex><base>tatar</base><ctag>subst:pl:nom:m2</ctag></lex>
    <lex><base>tatar</base><ctag>subst:pl:acc:m2</ctag></lex>
    <lex><base>tatar</base><ctag>subst:pl:voc:m2</ctag></lex>
    <lex disamb="1"><base>tatar</base><ctag>subst:pl:nom:m3</ctag></lex>
    <lex><base>tatar</base><ctag>subst:pl:acc:m3</ctag></lex>
    <lex><base>tatar</base><ctag>subst:pl:voc:m3</ctag></lex>
    <ann chan="nam">2</ann>
   </tok>
   <ns/>
   <tok>
    <orth>.</orth>
    <lex disamb="1"><base>.</base><ctag>interp</ctag></lex>
    <ann chan="nam">0</ann>
   </tok>
  </sentence>
 </chunk>
 <chunk id="ch6">
  <sentence id="sent12">
   <tok>
    <orth>Druga</orth>
    <lex><base>druga</base><ctag>subst:sg:nom:f</ctag></lex>
    <lex><base>druga</base><ctag>subst:sg:voc:f</ctag></lex>
    <lex disamb="1"><base>drugi</base><ctag>adj:sg:nom:f:pos</ctag></lex>
    <lex><base>drugi</base><ctag>adj:sg:voc:f:pos</ctag></lex>
    <ann chan="nam">0</ann>
   </tok>
   <tok>
    <orth>mówi</orth>
    <lex disamb="1"><base>mówić</base><ctag>fin:sg:ter:imperf</ctag></lex>
    <ann chan="nam">0</ann>
   </tok>
   <tok>
    <orth>o</orth>
    <lex><base>o</base><ctag>interj</ctag></lex>
    <lex><base>o</base><ctag>prep:acc</ctag></lex>
    <lex disamb="1"><base>o</base><ctag>prep:loc</ctag></lex>
    <lex><base>ojciec</base><ctag>brev:pun</ctag></lex>
    <ann chan="nam">0</ann>
   </tok>
   <tok>
    <orth>odstąpieniu</orth>
    <lex><base>odstąpić</base><ctag>ger:sg:dat:n:perf:aff</ctag></lex>
    <lex disamb="1"><base>odstąpić</base><ctag>ger:sg:loc:n:perf:aff</ctag></lex>
    <ann chan="nam">0</ann>
   </tok>
   <tok>
    <orth>Tatarów</orth>
    <lex disamb="1"><base>Tatar</base><ctag>subst:pl:gen:m1</ctag></lex>
    <lex><base>Tatar</base><ctag>subst:pl:acc:m1</ctag></lex>
    <lex><base>tatar</base><ctag>subst:pl:gen:m2</ctag></lex>
    <lex><base>tatar</base><ctag>subst:pl:gen:m3</ctag></lex>
    <ann chan="nam">1</ann>
   </tok>
   <tok>
    <orth>od</orth>
    <lex><base>Oda</base><ctag>subst:pl:gen:f</ctag></lex>
    <lex disamb="1"><base>od</base><ctag>prep:gen:nwok</ctag></lex>
    <ann chan="nam">0</ann>
   </tok>
   <tok>
    <orth>Lublina</orth>
    <lex disamb="1"><base>Lublin</base><ctag>subst:sg:gen:m3</ctag></lex>
    <lex disamb="1"><base>lublin</base><ctag>subst:sg:gen:m3</ctag></lex>
    <ann chan="nam">2</ann>
   </tok>
   <tok>
    <orth>po</orth>
    <lex><base>PO</base><ctag>subst:sg:nom:f</ctag></lex>
    <lex><base>PO</base><ctag>subst:sg:gen:f</ctag></lex>
    <lex><base>PO</base><ctag>subst:sg:dat:f</ctag></lex>
    <lex><base>PO</base><ctag>subst:sg:acc:f</ctag></lex>
    <lex><base>PO</base><ctag>subst:sg:inst:f</ctag></lex>
    <lex><base>PO</base><ctag>subst:sg:loc:f</ctag></lex>
    <lex><base>PO</base><ctag>subst:sg:voc:f</ctag></lex>
    <lex><base>PO</base><ctag>subst:sg:nom:n</ctag></lex>
    <lex><base>PO</base><ctag>subst:sg:gen:n</ctag></lex>
    <lex><base>PO</base><ctag>subst:sg:dat:n</ctag></lex>
    <lex><base>PO</base><ctag>subst:sg:acc:n</ctag></lex>
    <lex><base>PO</base><ctag>subst:sg:inst:n</ctag></lex>
    <lex><base>PO</base><ctag>subst:sg:loc:n</ctag></lex>
    <lex><base>PO</base><ctag>subst:sg:voc:n</ctag></lex>
    <lex><base>PO</base><ctag>subst:pl:nom:f</ctag></lex>
    <lex><base>PO</base><ctag>subst:pl:gen:f</ctag></lex>
    <lex><base>PO</base><ctag>subst:pl:dat:f</ctag></lex>
    <lex><base>PO</base><ctag>subst:pl:acc:f</ctag></lex>
    <lex><base>PO</base><ctag>subst:pl:inst:f</ctag></lex>
    <lex><base>PO</base><ctag>subst:pl:loc:f</ctag></lex>
    <lex><base>PO</base><ctag>subst:pl:voc:f</ctag></lex>
    <lex><base>PO</base><ctag>subst:pl:nom:n</ctag></lex>
    <lex><base>PO</base><ctag>subst:pl:gen:n</ctag></lex>
    <lex><base>PO</base><ctag>subst:pl:dat:n</ctag></lex>
    <lex><base>PO</base><ctag>subst:pl:acc:n</ctag></lex>
    <lex><base>PO</base><ctag>subst:pl:inst:n</ctag></lex>
    <lex><base>PO</base><ctag>subst:pl:loc:n</ctag></lex>
    <lex><base>PO</base><ctag>subst:pl:voc:n</ctag></lex>
    <lex><base>po</base><ctag>prep:acc</ctag></lex>
    <lex disamb="1"><base>po</base><ctag>prep:loc</ctag></lex>
    <ann chan="nam">0</ann>
   </tok>
   <tok>
    <orth>śmierci</orth>
    <lex><base>śmierć</base><ctag>subst:sg:gen:f</ctag></lex>
    <lex><base>śmierć</base><ctag>subst:sg:dat:f</ctag></lex>
    <lex disamb="1"><base>śmierć</base><ctag>subst:sg:loc:f</ctag></lex>
    <lex><base>śmierć</base><ctag>subst:sg:voc:f</ctag></lex>
    <lex><base>śmierć</base><ctag>subst:pl:nom:f</ctag></lex>
    <lex><base>śmierć</base><ctag>subst:pl:gen:f</ctag></lex>
    <lex><base>śmierć</base><ctag>subst:pl:acc:f</ctag></lex>
    <lex><base>śmierć</base><ctag>subst:pl:voc:f</ctag></lex>
    <ann chan="nam">0</ann>
   </tok>
   <tok>
    <orth>ich</orth>
    <lex disamb="1"><base>on</base><ctag>ppron3:pl:gen:m1:ter:akc:npraep</ctag></lex>
    <lex><base>on</base><ctag>ppron3:pl:gen:m1:ter:nakc:npraep</ctag></lex>
    <lex><base>on</base><ctag>ppron3:pl:acc:m1:ter:akc:npraep</ctag></lex>
    <lex><base>on</base><ctag>ppron3:pl:acc:m1:ter:nakc:npraep</ctag></lex>
    <lex><base>on</base><ctag>ppron3:pl:gen:m2:ter:akc:npraep</ctag></lex>
    <lex><base>on</base><ctag>ppron3:pl:gen:m2:ter:nakc:npraep</ctag></lex>
    <lex><base>on</base><ctag>ppron3:pl:gen:m3:ter:akc:npraep</ctag></lex>
    <lex><base>on</base><ctag>ppron3:pl:gen:m3:ter:nakc:npraep</ctag></lex>
    <lex><base>on</base><ctag>ppron3:pl:gen:f:ter:akc:npraep</ctag></lex>
    <lex><base>on</base><ctag>ppron3:pl:gen:f:ter:nakc:npraep</ctag></lex>
    <lex><base>on</base><ctag>ppron3:pl:gen:n:ter:akc:npraep</ctag></lex>
    <lex><base>on</base><ctag>ppron3:pl:gen:n:ter:nakc:npraep</ctag></lex>
    <ann chan="nam">0</ann>
   </tok>
   <tok>
    <orth>dowódcy</orth>
    <lex disamb="1"><base>dowódca</base><ctag>subst:sg:gen:m1</ctag></lex>
    <lex><base>dowódca</base><ctag>subst:sg:dat:m1</ctag></lex>
    <lex><base>dowódca</base><ctag>subst:sg:loc:m1</ctag></lex>
    <lex><base>dowódca</base><ctag>subst:pl:nom:m1</ctag></lex>
    <lex><base>dowódca</base><ctag>subst:pl:voc:m1</ctag></lex>
    <ann chan="nam">0</ann>
   </tok>
   <ns/>
   <tok>
    <orth>,</orth>
    <lex disamb="1"><base>,</base><ctag>interp</ctag></lex>
    <ann chan="nam">0</ann>
   </tok>
   <tok>
    <orth>który</orth>
    <lex disamb="1"><base>który</base><ctag>adj:sg:nom:m1:pos</ctag></lex>
    <lex><base>który</base><ctag>adj:sg:voc:m1:pos</ctag></lex>
    <lex><base>który</base><ctag>adj:sg:nom:m2:pos</ctag></lex>
    <lex><base>który</base><ctag>adj:sg:voc:m2:pos</ctag></lex>
    <lex><base>który</base><ctag>adj:sg:nom:m3:pos</ctag></lex>
    <lex><base>który</base><ctag>adj:sg:acc:m3:pos</ctag></lex>
    <lex><base>który</base><ctag>adj:sg:voc:m3:pos</ctag></lex>
    <ann chan="nam">0</ann>
   </tok>
   <tok>
    <orth>miał</orth>
    <lex><base>miał</base><ctag>subst:sg:nom:m3</ctag></lex>
    <lex><base>miał</base><ctag>subst:sg:acc:m3</ctag></lex>
    <lex disamb="1"><base>mieć</base><ctag>praet:sg:m1:imperf</ctag></lex>
    <lex><base>mieć</base><ctag>praet:sg:m2:imperf</ctag></lex>
    <lex><base>mieć</base><ctag>praet:sg:m3:imperf</ctag></lex>
    <ann chan="nam">0</ann>
   </tok>
   <tok>
    <orth>zginąć</orth>
    <lex disamb="1"><base>zginąć</base><ctag>inf:perf</ctag></lex>
    <ann chan="nam">0</ann>
   </tok>
   <tok>
    <orth>od</orth>
    <lex><base>Oda</base><ctag>subst:pl:gen:f</ctag></lex>
    <lex disamb="1"><base>od</base><ctag>prep:gen:nwok</ctag></lex>
    <ann chan="nam">0</ann>
   </tok>
   <tok>
    <orth>strzały</orth>
    <lex><base>strzał</base><ctag>subst:pl:nom:m3</ctag></lex>
    <lex><base>strzał</base><ctag>subst:pl:acc:m3</ctag></lex>
    <lex><base>strzał</base><ctag>subst:pl:voc:m3</ctag></lex>
    <lex disamb="1"><base>strzała</base><ctag>subst:sg:gen:f</ctag></lex>
    <lex><base>strzała</base><ctag>subst:pl:nom:f</ctag></lex>
    <lex><base>strzała</base><ctag>subst:pl:acc:f</ctag></lex>
    <lex><base>strzała</base><ctag>subst:pl:voc:f</ctag></lex>
    <ann chan="nam">0</ann>
   </tok>
   <tok>
    <orth>lubelskiego</orth>
    <lex><base>Lubelskie</base><ctag>subst:sg:gen:n</ctag></lex>
    <lex disamb="1"><base>lubelski</base><ctag>adj:sg:gen:m1:pos</ctag></lex>
    <lex><base>lubelski</base><ctag>adj:sg:acc:m1:pos</ctag></lex>
    <lex><base>lubelski</base><ctag>adj:sg:gen:m2:pos</ctag></lex>
    <lex><base>lubelski</base><ctag>adj:sg:acc:m2:pos</ctag></lex>
    <lex><base>lubelski</base><ctag>adj:sg:gen:m3:pos</ctag></lex>
    <lex><base>lubelski</base><ctag>adj:sg:gen:n:pos</ctag></lex>
    <ann chan="nam">3</ann>
   </tok>
   <tok>
    <orth>łucznika</orth>
    <lex disamb="1"><base>łucznik</base><ctag>subst:sg:gen:m1</ctag></lex>
    <lex><base>łucznik</base><ctag>subst:sg:acc:m1</ctag></lex>
    <ann chan="nam">0</ann>
   </tok>
   <ns/>
   <tok>
    <orth>.</orth>
    <lex disamb="1"><base>.</base><ctag>interp</ctag></lex>
    <ann chan="nam">0</ann>
   </tok>
  </sentence>
 </chunk>
 <chunk id="ch7">
  <sentence id="sent13">
   <tok>
    <orth>Kampania</orth>
    <lex disamb="1"><base>Kampania</base><ctag>subst:sg:nom:f</ctag></lex>
    <lex disamb="1"><base>kampania</base><ctag>subst:sg:nom:f</ctag></lex>
    <ann chan="nam">0</ann>
   </tok>
   <tok>
    <orth>ruska</orth>
    <lex><base>Rusek</base><ctag>subst:sg:gen:m1</ctag></lex>
    <lex><base>Rusek</base><ctag>subst:sg:acc:m1</ctag></lex>
    <lex><base>rusek</base><ctag>subst:sg:gen:m2</ctag></lex>
    <lex><base>rusek</base><ctag>subst:sg:acc:m2</ctag></lex>
    <lex><base>ruska</base><ctag>subst:sg:nom:f</ctag></lex>
    <lex disamb="1"><base>ruski</base><ctag>adj:sg:nom:f:pos</ctag></lex>
    <lex><base>ruski</base><ctag>adj:sg:voc:f:pos</ctag></lex>
    <ann chan="nam">0</ann>
   </tok>
   <tok>
    <orth>Kazimierza</orth>
    <lex disamb="1"><base>Kazimierz</base><ctag>subst:sg:gen:m1</ctag></lex>
    <lex><base>Kazimierz</base><ctag>subst:sg:acc:m1</ctag></lex>
    <lex><base>Kazimierz</base><ctag>subst:sg:gen:m3</ctag></lex>
    <ann chan="nam">1</ann>
   </tok>
   <tok>
    <orth>Wielkiego</orth>
    <lex disamb="1"><base>wielki</base><ctag>adj:sg:gen:m1:pos</ctag></lex>
    <lex><base>wielki</base><ctag>adj:sg:acc:m1:pos</ctag></lex>
    <lex><base>wielki</base><ctag>adj:sg:gen:m2:pos</ctag></lex>
    <lex><base>wielki</base><ctag>adj:sg:acc:m2:pos</ctag></lex>
    <lex><base>wielki</base><ctag>adj:sg:gen:m3:pos</ctag></lex>
    <lex><base>wielki</base><ctag>adj:sg:gen:n:pos</ctag></lex>
    <lex><base>wielki</base><ctag>subst:sg:gen:m1</ctag></lex>
    <lex><base>wielki</base><ctag>subst:sg:acc:m1</ctag></lex>
    <ann chan="nam">1</ann>
   </tok>
   <tok>
    <orth>z</orth>
    <lex disamb="1"><base>z</base><ctag>prep:gen:nwok</ctag></lex>
    <lex><base>z</base><ctag>prep:acc:nwok</ctag></lex>
    <lex><base>z</base><ctag>prep:inst:nwok</ctag></lex>
    <lex><base>z</base><ctag>qub</ctag></lex>
    <lex><base>zeszyt</base><ctag>brev:pun</ctag></lex>
    <ann chan="nam">0</ann>
   </tok>
   <tok>
    <orth>lat</orth>
    <lex><base>lato</base><ctag>subst:pl:gen:n</ctag></lex>
    <lex disamb="1"><base>rok</base><ctag>subst:pl:gen:m3</ctag></lex>
    <ann chan="nam">0</ann>
   </tok>
   <tok>
    <orth>1340</orth>
    <lex><base>1340</base><ctag>ign</ctag></lex>
    <lex disamb="1"><base>1340</base><ctag>num:pl:nom:m3:rec</ctag></lex>
    <ann chan="nam">0</ann>
   </tok>
   <tok>
    <orth>i</orth>
    <lex disamb="1"><base>i</base><ctag>conj</ctag></lex>
    <lex><base>i</base><ctag>interj</ctag></lex>
    <lex><base>i</base><ctag>qub</ctag></lex>
    <ann chan="nam">0</ann>
   </tok>
   <tok>
    <orth>1341</orth>
    <lex><base>1341</base><ctag>ign</ctag></lex>
    <lex disamb="1"><base>1341</base><ctag>num:pl:nom:m3:rec</ctag></lex>
    <ann chan="nam">0</ann>
   </tok>
   <tok>
    <orth>zakończyła</orth>
    <lex disamb="1"><base>zakończyć</base><ctag>praet:sg:f:perf</ctag></lex>
    <ann chan="nam">0</ann>
   </tok>
   <tok>
    <orth>się</orth>
    <lex disamb="1"><base>się</base><ctag>qub</ctag></lex>
    <ann chan="nam">0</ann>
   </tok>
   <tok>
    <orth>kompromisem</orth>
    <lex disamb="1"><base>kompromis</base><ctag>subst:sg:inst:m3</ctag></lex>
    <ann chan="nam">0</ann>
   </tok>
   <ns/>
   <tok>
    <orth>.</orth>
    <lex disamb="1"><base>.</base><ctag>interp</ctag></lex>
    <ann chan="nam">0</ann>
   </tok>
  </sentence>
  <sentence id="sent14">
   <tok>
    <orth>Przywódca</orth>
    <lex disamb="1"><base>przywódca</base><ctag>subst:sg:nom:m1</ctag></lex>
    <ann chan="nam">0</ann>
   </tok>
   <tok>
    <orth>bojarów</orth>
    <lex disamb="1"><base>bojar</base><ctag>subst:pl:gen:m1</ctag></lex>
    <lex><base>bojar</base><ctag>subst:pl:acc:m1</ctag></lex>
    <ann chan="nam">0</ann>
   </tok>
   <tok>
    <orth>ruskich</orth>
    <lex><base>Ruski</base><ctag>subst:pl:gen:m1</ctag></lex>
    <lex><base>Ruski</base><ctag>subst:pl:acc:m1</ctag></lex>
    <lex><base>Ruski</base><ctag>subst:pl:loc:m1</ctag></lex>
    <lex disamb="1"><base>ruski</base><ctag>adj:pl:gen:m1:pos</ctag></lex>
    <lex><base>ruski</base><ctag>adj:pl:acc:m1:pos</ctag></lex>
    <lex><base>ruski</base><ctag>adj:pl:loc:m1:pos</ctag></lex>
    <lex><base>ruski</base><ctag>adj:pl:gen:m2:pos</ctag></lex>
    <lex><base>ruski</base><ctag>adj:pl:loc:m2:pos</ctag></lex>
    <lex><base>ruski</base><ctag>adj:pl:gen:m3:pos</ctag></lex>
    <lex><base>ruski</base><ctag>adj:pl:loc:m3:pos</ctag></lex>
    <lex><base>ruski</base><ctag>adj:pl:gen:f:pos</ctag></lex>
    <lex><base>ruski</base><ctag>adj:pl:loc:f:pos</ctag></lex>
    <lex><base>ruski</base><ctag>adj:pl:gen:n:pos</ctag></lex>
    <lex><base>ruski</base><ctag>adj:pl:loc:n:pos</ctag></lex>
    <lex><base>ruski</base><ctag>subst:pl:gen:m3</ctag></lex>
    <lex><base>ruski</base><ctag>subst:pl:loc:m3</ctag></lex>
    <lex><base>ruskie</base><ctag>subst:pl:gen:n</ctag></lex>
    <lex><base>ruskie</base><ctag>subst:pl:loc:n</ctag></lex>
    <ann chan="nam">1</ann>
   </tok>
   <tok>
    <orth>Dymitr</orth>
    <lex disamb="1"><base>Dymitr</base><ctag>subst:sg:nom:m1</ctag></lex>
    <ann chan="nam">2</ann>
   </tok>
   <tok>
    <orth>Detko</orth>
    <lex><base>Detko</base><ctag>ign</ctag></lex>
    <lex disamb="1"><base>detko</base><ctag>subst:sg:nom:m1</ctag></lex>
    <ann chan="nam">2</ann>
   </tok>
   <tok>
    <orth>uznał</orth>
    <lex disamb="1"><base>uznać</base><ctag>praet:sg:m1:perf</ctag></lex>
    <lex><base>uznać</base><ctag>praet:sg:m2:perf</ctag></lex>
    <lex><base>uznać</base><ctag>praet:sg:m3:perf</ctag></lex>
    <ann chan="nam">0</ann>
   </tok>
   <tok>
    <orth>zwierzchnictwo</orth>
    <lex><base>zwierzchnictwo</base><ctag>subst:sg:nom:n</ctag></lex>
    <lex disamb="1"><base>zwierzchnictwo</base><ctag>subst:sg:acc:n</ctag></lex>
    <lex><base>zwierzchnictwo</base><ctag>subst:sg:voc:n</ctag></lex>
    <ann chan="nam">0</ann>
   </tok>
   <tok>
    <orth>króla</orth>
    <lex disamb="1"><base>Król</base><ctag>subst:sg:gen:m1</ctag></lex>
    <lex><base>Król</base><ctag>subst:sg:acc:m1</ctag></lex>
    <lex disamb="1"><base>król</base><ctag>subst:sg:gen:m1</ctag></lex>
    <lex><base>król</base><ctag>subst:sg:acc:m1</ctag></lex>
    <lex><base>król</base><ctag>subst:sg:gen:m2</ctag></lex>
    <lex><base>król</base><ctag>subst:sg:acc:m2</ctag></lex>
    <ann chan="nam">0</ann>
   </tok>
   <tok>
    <orth>Polskiego</orth>
    <lex disamb="1"><base>polski</base><ctag>adj:sg:gen:m1:pos</ctag></lex>
    <lex><base>polski</base><ctag>adj:sg:acc:m1:pos</ctag></lex>
    <lex><base>polski</base><ctag>adj:sg:gen:m2:pos</ctag></lex>
    <lex><base>polski</base><ctag>adj:sg:acc:m2:pos</ctag></lex>
    <lex><base>polski</base><ctag>adj:sg:gen:m3:pos</ctag></lex>
    <lex><base>polski</base><ctag>adj:sg:gen:n:pos</ctag></lex>
    <lex><base>polski</base><ctag>subst:sg:gen:m3</ctag></lex>
    <lex><base>polskie</base><ctag>subst:sg:gen:n</ctag></lex>
    <ann chan="nam">3</ann>
   </tok>
   <tok>
    <orth>przyjmując</orth>
    <lex disamb="1"><base>przyjmować</base><ctag>pcon:imperf</ctag></lex>
    <ann chan="nam">0</ann>
   </tok>
   <tok>
    <orth>tytuł</orth>
    <lex><base>tytuł</base><ctag>subst:sg:nom:m3</ctag></lex>
    <lex disamb="1"><base>tytuł</base><ctag>subst:sg:acc:m3</ctag></lex>
    <ann chan="nam">0</ann>
   </tok>
   <tok>
    <orth>namiestnika</orth>
    <lex disamb="1"><base>namiestnik</base><ctag>subst:sg:gen:m1</ctag></lex>
    <lex><base>namiestnik</base><ctag>subst:sg:acc:m1</ctag></lex>
    <ann chan="nam">0</ann>
   </tok>
   <tok>
    <orth>królewskiego</orth>
    <lex disamb="1"><base>królewski</base><ctag>adj:sg:gen:m1:pos</ctag></lex>
    <lex><base>królewski</base><ctag>adj:sg:acc:m1:pos</ctag></lex>
    <lex><base>królewski</base><ctag>adj:sg:gen:m2:pos</ctag></lex>
    <lex><base>królewski</base><ctag>adj:sg:acc:m2:pos</ctag></lex>
    <lex><base>królewski</base><ctag>adj:sg:gen:m3:pos</ctag></lex>
    <lex><base>królewski</base><ctag>adj:sg:gen:n:pos</ctag></lex>
    <ann chan="nam">0</ann>
   </tok>
   <tok>
    <orth>Rusi</orth>
    <lex disamb="1"><base>Ruś</base><ctag>subst:sg:gen:f</ctag></lex>
    <lex><base>Ruś</base><ctag>subst:sg:dat:f</ctag></lex>
    <lex><base>Ruś</base><ctag>subst:sg:loc:f</ctag></lex>
    <lex><base>Ruś</base><ctag>subst:sg:voc:f</ctag></lex>
    <lex><base>Ruś</base><ctag>subst:pl:gen:f</ctag></lex>
    <lex><base>rusy</base><ctag>adj:pl:nom:m1:pos</ctag></lex>
    <lex><base>rusy</base><ctag>adj:pl:voc:m1:pos</ctag></lex>
    <ann chan="nam">4</ann>
   </tok>
   <ns/>
   <tok>
    <orth>.</orth>
    <lex disamb="1"><base>.</base><ctag>interp</ctag></lex>
    <ann chan="nam">0</ann>
   </tok>
  </sentence>
  <sentence id="sent15">
   <tok>
    <orth>Kazimierz</orth>
    <lex disamb="1"><base>Kazimierz</base><ctag>subst:sg:nom:m1</ctag></lex>
    <lex><base>Kazimierz</base><ctag>subst:sg:nom:m3</ctag></lex>
    <lex><base>Kazimierz</base><ctag>subst:sg:acc:m3</ctag></lex>
    <ann chan="nam">1</ann>
   </tok>
   <tok>
    <orth>Wielki</orth>
    <lex disamb="1"><base>wielki</base><ctag>adj:sg:nom:m1:pos</ctag></lex>
    <lex><base>wielki</base><ctag>adj:sg:voc:m1:pos</ctag></lex>
    <lex><base>wielki</base><ctag>adj:sg:nom:m2:pos</ctag></lex>
    <lex><base>wielki</base><ctag>adj:sg:voc:m2:pos</ctag></lex>
    <lex><base>wielki</base><ctag>adj:sg:nom:m3:pos</ctag></lex>
    <lex><base>wielki</base><ctag>adj:sg:acc:m3:pos</ctag></lex>
    <lex><base>wielki</base><ctag>adj:sg:voc:m3:pos</ctag></lex>
    <lex><base>wielki</base><ctag>subst:sg:nom:m1</ctag></lex>
    <lex><base>wielki</base><ctag>subst:sg:voc:m1</ctag></lex>
    <ann chan="nam">1</ann>
   </tok>
   <tok>
    <orth>wcielił</orth>
    <lex disamb="1"><base>wcielić</base><ctag>praet:sg:m1:perf</ctag></lex>
    <lex><base>wcielić</base><ctag>praet:sg:m2:perf</ctag></lex>
    <lex><base>wcielić</base><ctag>praet:sg:m3:perf</ctag></lex>
    <ann chan="nam">0</ann>
   </tok>
   <tok>
    <orth>bezpośrednio</orth>
    <lex disamb="1"><base>bezpośrednio</base><ctag>adv:pos</ctag></lex>
    <ann chan="nam">0</ann>
   </tok>
   <tok>
    <orth>od</orth>
    <lex><base>Oda</base><ctag>subst:pl:gen:f</ctag></lex>
    <lex disamb="1"><base>od</base><ctag>prep:gen:nwok</ctag></lex>
    <ann chan="nam">0</ann>
   </tok>
   <tok>
    <orth>korony</orth>
    <lex disamb="1"><base>korona</base><ctag>subst:sg:gen:f</ctag></lex>
    <lex><base>korona</base><ctag>subst:pl:nom:f</ctag></lex>
    <lex><base>korona</base><ctag>subst:pl:acc:f</ctag></lex>
    <lex><base>korona</base><ctag>subst:pl:voc:f</ctag></lex>
    <ann chan="nam">0</ann>
   </tok>
   <tok>
    <orth>ziemie</orth>
    <lex><base>Ziemia</base><ctag>subst:pl:nom:f</ctag></lex>
    <lex disamb="1"><base>Ziemia</base><ctag>subst:pl:acc:f</ctag></lex>
    <lex><base>Ziemia</base><ctag>subst:pl:voc:f</ctag></lex>
    <lex><base>ziemia</base><ctag>subst:pl:nom:f</ctag></lex>
    <lex disamb="1"><base>ziemia</base><ctag>subst:pl:acc:f</ctag></lex>
    <lex><base>ziemia</base><ctag>subst:pl:voc:f</ctag></lex>
    <ann chan="nam">2</ann>
   </tok>
   <tok>
    <orth>sanocką</orth>
    <lex disamb="1"><base>sanocki</base><ctag>adj:sg:acc:f:pos</ctag></lex>
    <lex><base>sanocki</base><ctag>adj:sg:inst:f:pos</ctag></lex>
    <ann chan="nam">2</ann>
   </tok>
   <tok>
    <orth>i</orth>
    <lex disamb="1"><base>i</base><ctag>conj</ctag></lex>
    <lex><base>i</base><ctag>interj</ctag></lex>
    <lex><base>i</base><ctag>qub</ctag></lex>
    <ann chan="nam">0</ann>
   </tok>
   <tok>
    <orth>okolice</orth>
    <lex><base>okolica</base><ctag>subst:pl:nom:f</ctag></lex>
    <lex disamb="1"><base>okolica</base><ctag>subst:pl:acc:f</ctag></lex>
    <lex><base>okolica</base><ctag>subst:pl:voc:f</ctag></lex>
    <ann chan="nam">0</ann>
   </tok>
   <tok>
    <orth>Rzeszowa</orth>
    <lex disamb="1"><base>Rzeszów</base><ctag>subst:sg:gen:m3</ctag></lex>
    <ann chan="nam">3</ann>
   </tok>
   <tok>
    <orth>oraz</orth>
    <lex disamb="1"><base>oraz</base><ctag>conj</ctag></lex>
    <ann chan="nam">0</ann>
   </tok>
   <tok>
    <orth>poprzysiągł</orth>
    <lex disamb="1"><base>poprzysiąc</base><ctag>praet:sg:m1:perf</ctag></lex>
    <lex><base>poprzysiąc</base><ctag>praet:sg:m2:perf</ctag></lex>
    <lex><base>poprzysiąc</base><ctag>praet:sg:m3:perf</ctag></lex>
    <lex disamb="1"><base>poprzysięgnąć</base><ctag>praet:sg:m1:perf</ctag></lex>
    <lex><base>poprzysięgnąć</base><ctag>praet:sg:m2:perf</ctag></lex>
    <lex><base>poprzysięgnąć</base><ctag>praet:sg:m3:perf</ctag></lex>
    <ann chan="nam">0</ann>
   </tok>
   <tok>
    <orth>poszanowanie</orth>
    <lex><base>poszanowanie</base><ctag>subst:sg:nom:n</ctag></lex>
    <lex><base>poszanowanie</base><ctag>subst:sg:acc:n</ctag></lex>
    <lex><base>poszanowanie</base><ctag>subst:sg:voc:n</ctag></lex>
    <lex><base>poszanować</base><ctag>ger:sg:nom:n:perf:aff</ctag></lex>
    <lex disamb="1"><base>poszanować</base><ctag>ger:sg:acc:n:perf:aff</ctag></lex>
    <ann chan="nam">0</ann>
   </tok>
   <tok>
    <orth>obyczajów</orth>
    <lex disamb="1"><base>obyczaj</base><ctag>subst:pl:gen:m3</ctag></lex>
    <ann chan="nam">0</ann>
   </tok>
   <tok>
    <orth>zajętych</orth>
    <lex><base>zająć</base><ctag>ppas:pl:gen:m1:perf:aff</ctag></lex>
    <lex><base>zająć</base><ctag>ppas:pl:acc:m1:perf:aff</ctag></lex>
    <lex><base>zająć</base><ctag>ppas:pl:loc:m1:perf:aff</ctag></lex>
    <lex><base>zająć</base><ctag>ppas:pl:gen:m2:perf:aff</ctag></lex>
    <lex><base>zająć</base><ctag>ppas:pl:loc:m2:perf:aff</ctag></lex>
    <lex><base>zająć</base><ctag>ppas:pl:gen:m3:perf:aff</ctag></lex>
    <lex><base>zająć</base><ctag>ppas:pl:loc:m3:perf:aff</ctag></lex>
    <lex><base>zająć</base><ctag>ppas:pl:gen:f:perf:aff</ctag></lex>
    <lex><base>zająć</base><ctag>ppas:pl:loc:f:perf:aff</ctag></lex>
    <lex><base>zająć</base><ctag>ppas:pl:gen:n:perf:aff</ctag></lex>
    <lex><base>zająć</base><ctag>ppas:pl:loc:n:perf:aff</ctag></lex>
    <lex><base>zajęty</base><ctag>adj:pl:gen:m1:pos</ctag></lex>
    <lex><base>zajęty</base><ctag>adj:pl:acc:m1:pos</ctag></lex>
    <lex><base>zajęty</base><ctag>adj:pl:loc:m1:pos</ctag></lex>
    <lex><base>zajęty</base><ctag>adj:pl:gen:m2:pos</ctag></lex>
    <lex><base>zajęty</base><ctag>adj:pl:loc:m2:pos</ctag></lex>
    <lex><base>zajęty</base><ctag>adj:pl:gen:m3:pos</ctag></lex>
    <lex><base>zajęty</base><ctag>adj:pl:loc:m3:pos</ctag></lex>
    <lex disamb="1"><base>zajęty</base><ctag>adj:pl:gen:f:pos</ctag></lex>
    <lex><base>zajęty</base><ctag>adj:pl:loc:f:pos</ctag></lex>
    <lex><base>zajęty</base><ctag>adj:pl:gen:n:pos</ctag></lex>
    <lex><base>zajęty</base><ctag>adj:pl:loc:n:pos</ctag></lex>
    <ann chan="nam">0</ann>
   </tok>
   <tok>
    <orth>ziem</orth>
    <lex disamb="1"><base>Ziemia</base><ctag>subst:pl:gen:f</ctag></lex>
    <lex><base>ziem</base><ctag>burk</ctag></lex>
    <lex disamb="1"><base>ziemia</base><ctag>subst:pl:gen:f</ctag></lex>
    <ann chan="nam">0</ann>
   </tok>
   <tok>
    <orth>i</orth>
    <lex disamb="1"><base>i</base><ctag>conj</ctag></lex>
    <lex><base>i</base><ctag>interj</ctag></lex>
    <lex><base>i</base><ctag>qub</ctag></lex>
    <ann chan="nam">0</ann>
   </tok>
   <tok>
    <orth>wiary</orth>
    <lex disamb="1"><base>wiara</base><ctag>subst:sg:gen:f</ctag></lex>
    <lex><base>wiara</base><ctag>subst:pl:nom:f</ctag></lex>
    <lex><base>wiara</base><ctag>subst:pl:acc:f</ctag></lex>
    <lex><base>wiara</base><ctag>subst:pl:voc:f</ctag></lex>
    <ann chan="nam">0</ann>
   </tok>
   <tok>
    <orth>prawosławnej</orth>
    <lex><base>prawosławna</base><ctag>subst:sg:gen:f</ctag></lex>
    <lex><base>prawosławna</base><ctag>subst:sg:dat:f</ctag></lex>
    <lex><base>prawosławna</base><ctag>subst:sg:loc:f</ctag></lex>
    <lex disamb="1"><base>prawosławny</base><ctag>adj:sg:gen:f:pos</ctag></lex>
    <lex><base>prawosławny</base><ctag>adj:sg:dat:f:pos</ctag></lex>
    <lex><base>prawosławny</base><ctag>adj:sg:loc:f:pos</ctag></lex>
    <ann chan="nam">0</ann>
   </tok>
   <ns/>
   <tok>
    <orth>.</orth>
    <lex disamb="1"><base>.</base><ctag>interp</ctag></lex>
    <ann chan="nam">0</ann>
   </tok>
  </sentence>
 </chunk>
</chunkList>